{"nodes": [{"id": "users_siltala_dev_personal_slk_internal_ui_themeswitcher_model_go", "label": "model.go", "file_type": "code", "source_file": "internal/ui/themeswitcher/model.go", "source_location": "L1"}, {"id": "themeswitcher_themescope", "label": "ThemeScope", "file_type": "code", "source_file": "internal/ui/themeswitcher/model.go", "source_location": "L16"}, {"id": "themeswitcher_themeresult", "label": "ThemeResult", "file_type": "code", "source_file": "internal/ui/themeswitcher/model.go", "source_location": "L24"}, {"id": "themeswitcher_model", "label": "Model", "file_type": "code", "source_file": "internal/ui/themeswitcher/model.go", "source_location": "L30"}, {"id": "themeswitcher_model_new", "label": "New()", "file_type": "code", "source_file": "internal/ui/themeswitcher/model.go", "source_location": "L41"}, {"id": "themeswitcher_model_setitems", "label": ".SetItems()", "file_type": "code", "source_file": "internal/ui/themeswitcher/model.go", "source_location": "L46"}, {"id": "themeswitcher_model_open", "label": ".Open()", "file_type": "code", "source_file": "internal/ui/themeswitcher/model.go", "source_location": "L52"}, {"id": "themeswitcher_model_openwithscope", "label": ".OpenWithScope()", "file_type": "code", "source_file": "internal/ui/themeswitcher/model.go", "source_location": "L59"}, {"id": "themeswitcher_model_scope", "label": ".Scope()", "file_type": "code", "source_file": "internal/ui/themeswitcher/model.go", "source_location": "L69"}, {"id": "themeswitcher_model_headertext", "label": ".HeaderText()", "file_type": "code", "source_file": "internal/ui/themeswitcher/model.go", "source_location": "L72"}, {"id": "themeswitcher_model_close", "label": ".Close()", "file_type": "code", "source_file": "internal/ui/themeswitcher/model.go", "source_location": "L75"}, {"id": "themeswitcher_model_isvisible", "label": ".IsVisible()", "file_type": "code", "source_file": "internal/ui/themeswitcher/model.go", "source_location": "L80"}, {"id": "themeswitcher_model_handlekey", "label": ".HandleKey()", "file_type": "code", "source_file": "internal/ui/themeswitcher/model.go", "source_location": "L86"}, {"id": "themeswitcher_model_filter", "label": ".filter()", "file_type": "code", "source_file": "internal/ui/themeswitcher/model.go", "source_location": "L131"}, {"id": "themeswitcher_model_viewoverlay", "label": ".ViewOverlay()", "file_type": "code", "source_file": "internal/ui/themeswitcher/model.go", "source_location": "L155"}, {"id": "themeswitcher_model_renderbox", "label": ".renderBox()", "file_type": "code", "source_file": "internal/ui/themeswitcher/model.go", "source_location": "L168"}], "edges": [{"source": "users_siltala_dev_personal_slk_internal_ui_themeswitcher_model_go", "target": "go_pkg_strings", "relation": "imports_from", "confidence": "EXTRACTED", "source_file": "internal/ui/themeswitcher/model.go", "source_location": "L4", "weight": 1.0, "context": "import"}, {"source": "users_siltala_dev_personal_slk_internal_ui_themeswitcher_model_go", "target": "go_pkg_charm_land_lipgloss_v2", "relation": "imports_from", "confidence": "EXTRACTED", "source_file": "internal/ui/themeswitcher/model.go", "source_location": "L6", "weight": 1.0, "context": "import"}, {"source": "users_siltala_dev_personal_slk_internal_ui_themeswitcher_model_go", "target": "go_pkg_github_com_gammons_slk_internal_text", "relation": "imports_from", "confidence": "EXTRACTED", "source_file": "internal/ui/themeswitcher/model.go", "source_location": "L7", "weight": 1.0, "context": "import"}, {"source": "users_siltala_dev_personal_slk_internal_ui_themeswitcher_model_go", "target": "go_pkg_github_com_gammons_slk_internal_ui_messages", "relation": "imports_from", "confidence": "EXTRACTED", "source_file": "internal/ui/themeswitcher/model.go", "source_location": "L8", "weight": 1.0, "context": "import"}, {"source": "users_siltala_dev_personal_slk_internal_ui_themeswitcher_model_go", "target": "go_pkg_github_com_gammons_slk_internal_ui_overlay", "relation": "imports_from", "confidence": "EXTRACTED", "source_file": "internal/ui/themeswitcher/model.go", "source_location": "L9", "weight": 1.0, "context": "import"}, {"source": "users_siltala_dev_personal_slk_internal_ui_themeswitcher_model_go", "target": "go_pkg_github_com_gammons_slk_internal_ui_styles", "relation": "imports_from", "confidence": "EXTRACTED", "source_file": "internal/ui/themeswitcher/model.go", "source_location": "L10", "weight": 1.0, "context": "import"}, {"source": "users_siltala_dev_personal_slk_internal_ui_themeswitcher_model_go", "target": "go_pkg_github_com_muesli_reflow_truncate", "relation": "imports_from", "confidence": "EXTRACTED", "source_file": "internal/ui/themeswitcher/model.go", "source_location": "L11", "weight": 1.0, "context": "import"}, {"source": "users_siltala_dev_personal_slk_internal_ui_themeswitcher_model_go", "target": "themeswitcher_themescope", "relation": "contains", "confidence": "EXTRACTED", "source_file": "internal/ui/themeswitcher/model.go", "source_location": "L16", "weight": 1.0}, {"source": "users_siltala_dev_personal_slk_internal_ui_themeswitcher_model_go", "target": "themeswitcher_themeresult", "relation": "contains", "confidence": "EXTRACTED", "source_file": "internal/ui/themeswitcher/model.go", "source_location": "L24", "weight": 1.0}, {"source": "themeswitcher_themeresult", "target": "themeswitcher_themescope", "relation": "references", "confidence": "EXTRACTED", "source_file": "internal/ui/themeswitcher/model.go", "source_location": "L26", "weight": 1.0, "context": "field"}, {"source": "users_siltala_dev_personal_slk_internal_ui_themeswitcher_model_go", "target": "themeswitcher_model", "relation": "contains", "confidence": "EXTRACTED", "source_file": "internal/ui/themeswitcher/model.go", "source_location": "L30", "weight": 1.0}, {"source": "themeswitcher_model", "target": "themeswitcher_themescope", "relation": "references", "confidence": "EXTRACTED", "source_file": "internal/ui/themeswitcher/model.go", "source_location": "L36", "weight": 1.0, "context": "field"}, {"source": "users_siltala_dev_personal_slk_internal_ui_themeswitcher_model_go", "target": "themeswitcher_model_new", "relation": "contains", "confidence": "EXTRACTED", "source_file": "internal/ui/themeswitcher/model.go", "source_location": "L41", "weight": 1.0}, {"source": "themeswitcher_model_new", "target": "themeswitcher_model", "relation": "references", "confidence": "EXTRACTED", "source_file": "internal/ui/themeswitcher/model.go", "source_location": "L41", "weight": 1.0, "context": "return_type"}, {"source": "themeswitcher_model", "target": "themeswitcher_model_setitems", "relation": "method", "confidence": "EXTRACTED", "source_file": "internal/ui/themeswitcher/model.go", "source_location": "L46", "weight": 1.0}, {"source": "themeswitcher_model", "target": "themeswitcher_model_open", "relation": "method", "confidence": "EXTRACTED", "source_file": "internal/ui/themeswitcher/model.go", "source_location": "L52", "weight": 1.0}, {"source": "themeswitcher_model", "target": "themeswitcher_model_openwithscope", "relation": "method", "confidence": "EXTRACTED", "source_file": "internal/ui/themeswitcher/model.go", "source_location": "L59", "weight": 1.0}, {"source": "themeswitcher_model_openwithscope", "target": "themeswitcher_themescope", "relation": "references", "confidence": "EXTRACTED", "source_file": "internal/ui/themeswitcher/model.go", "source_location": "L59", "weight": 1.0, "context": "parameter_type"}, {"source": "themeswitcher_model", "target": "themeswitcher_model_scope", "relation": "method", "confidence": "EXTRACTED", "source_file": "internal/ui/themeswitcher/model.go", "source_location": "L69", "weight": 1.0}, {"source": "themeswitcher_model_scope", "target": "themeswitcher_themescope", "relation": "references", "confidence": "EXTRACTED", "source_file": "internal/ui/themeswitcher/model.go", "source_location": "L69", "weight": 1.0, "context": "return_type"}, {"source": "themeswitcher_model", "target": "themeswitcher_model_headertext", "relation": "method", "confidence": "EXTRACTED", "source_file": "internal/ui/themeswitcher/model.go", "source_location": "L72", "weight": 1.0}, {"source": "themeswitcher_model", "target": "themeswitcher_model_close", "relation": "method", "confidence": "EXTRACTED", "source_file": "internal/ui/themeswitcher/model.go", "source_location": "L75", "weight": 1.0}, {"source": "themeswitcher_model", "target": "themeswitcher_model_isvisible", "relation": "method", "confidence": "EXTRACTED", "source_file": "internal/ui/themeswitcher/model.go", "source_location": "L80", "weight": 1.0}, {"source": "themeswitcher_model", "target": "themeswitcher_model_handlekey", "relation": "method", "confidence": "EXTRACTED", "source_file": "internal/ui/themeswitcher/model.go", "source_location": "L86", "weight": 1.0}, {"source": "themeswitcher_model_handlekey", "target": "themeswitcher_themeresult", "relation": "references", "confidence": "EXTRACTED", "source_file": "internal/ui/themeswitcher/model.go", "source_location": "L86", "weight": 1.0, "context": "return_type"}, {"source": "themeswitcher_model", "target": "themeswitcher_model_filter", "relation": "method", "confidence": "EXTRACTED", "source_file": "internal/ui/themeswitcher/model.go", "source_location": "L131", "weight": 1.0}, {"source": "themeswitcher_model", "target": "themeswitcher_model_viewoverlay", "relation": "method", "confidence": "EXTRACTED", "source_file": "internal/ui/themeswitcher/model.go", "source_location": "L155", "weight": 1.0}, {"source": "themeswitcher_model", "target": "themeswitcher_model_renderbox", "relation": "method", "confidence": "EXTRACTED", "source_file": "internal/ui/themeswitcher/model.go", "source_location": "L168", "weight": 1.0}, {"source": "themeswitcher_model_open", "target": "themeswitcher_model_openwithscope", "relation": "calls", "context": "call", "confidence": "EXTRACTED", "source_file": "internal/ui/themeswitcher/model.go", "source_location": "L53", "weight": 1.0}, {"source": "themeswitcher_model_handlekey", "target": "themeswitcher_model_close", "relation": "calls", "context": "call", "confidence": "EXTRACTED", "source_file": "internal/ui/themeswitcher/model.go", "source_location": "L96", "weight": 1.0}, {"source": "themeswitcher_model_viewoverlay", "target": "themeswitcher_model_renderbox", "relation": "calls", "context": "call", "confidence": "EXTRACTED", "source_file": "internal/ui/themeswitcher/model.go", "source_location": "L160", "weight": 1.0}], "raw_calls": [{"caller_nid": "themeswitcher_model_filter", "callee": "Fold", "is_member_call": false, "source_file": "/Users/siltala/dev/personal/slk/internal/ui/themeswitcher/model.go", "source_location": "L133"}, {"caller_nid": "themeswitcher_model_filter", "callee": "append", "is_member_call": false, "source_file": "/Users/siltala/dev/personal/slk/internal/ui/themeswitcher/model.go", "source_location": "L137"}, {"caller_nid": "themeswitcher_model_filter", "callee": "Fold", "is_member_call": false, "source_file": "/Users/siltala/dev/personal/slk/internal/ui/themeswitcher/model.go", "source_location": "L144"}, {"caller_nid": "themeswitcher_model_filter", "callee": "HasPrefix", "is_member_call": false, "source_file": "/Users/siltala/dev/personal/slk/internal/ui/themeswitcher/model.go", "source_location": "L145"}, {"caller_nid": "themeswitcher_model_filter", "callee": "append", "is_member_call": false, "source_file": "/Users/siltala/dev/personal/slk/internal/ui/themeswitcher/model.go", "source_location": "L146"}, {"caller_nid": "themeswitcher_model_filter", "callee": "Contains", "is_member_call": false, "source_file": "/Users/siltala/dev/personal/slk/internal/ui/themeswitcher/model.go", "source_location": "L147"}, {"caller_nid": "themeswitcher_model_filter", "callee": "append", "is_member_call": false, "source_file": "/Users/siltala/dev/personal/slk/internal/ui/themeswitcher/model.go", "source_location": "L148"}, {"caller_nid": "themeswitcher_model_filter", "callee": "append", "is_member_call": false, "source_file": "/Users/siltala/dev/personal/slk/internal/ui/themeswitcher/model.go", "source_location": "L151"}, {"caller_nid": "themeswitcher_model_viewoverlay", "callee": "DimmedOverlay", "is_member_call": false, "source_file": "/Users/siltala/dev/personal/slk/internal/ui/themeswitcher/model.go", "source_location": "L165"}, {"caller_nid": "themeswitcher_model_renderbox", "callee": "Render", "is_member_call": true, "source_file": "/Users/siltala/dev/personal/slk/internal/ui/themeswitcher/model.go", "source_location": "L190"}, {"caller_nid": "themeswitcher_model_renderbox", "callee": "Foreground", "is_member_call": true, "source_file": "/Users/siltala/dev/personal/slk/internal/ui/themeswitcher/model.go", "source_location": "L190"}, {"caller_nid": "themeswitcher_model_renderbox", "callee": "Background", "is_member_call": true, "source_file": "/Users/siltala/dev/personal/slk/internal/ui/themeswitcher/model.go", "source_location": "L190"}, {"caller_nid": "themeswitcher_model_renderbox", "callee": "Bold", "is_member_call": true, "source_file": "/Users/siltala/dev/personal/slk/internal/ui/themeswitcher/model.go", "source_location": "L190"}, {"caller_nid": "themeswitcher_model_renderbox", "callee": "NewStyle", "is_member_call": true, "source_file": "/Users/siltala/dev/personal/slk/internal/ui/themeswitcher/model.go", "source_location": "L190"}, {"caller_nid": "themeswitcher_model_renderbox", "callee": "Render", "is_member_call": true, "source_file": "/Users/siltala/dev/personal/slk/internal/ui/themeswitcher/model.go", "source_location": "L198"}, {"caller_nid": "themeswitcher_model_renderbox", "callee": "Foreground", "is_member_call": true, "source_file": "/Users/siltala/dev/personal/slk/internal/ui/themeswitcher/model.go", "source_location": "L198"}, {"caller_nid": "themeswitcher_model_renderbox", "callee": "Background", "is_member_call": true, "source_file": "/Users/siltala/dev/personal/slk/internal/ui/themeswitcher/model.go", "source_location": "L198"}, {"caller_nid": "themeswitcher_model_renderbox", "callee": "NewStyle", "is_member_call": true, "source_file": "/Users/siltala/dev/personal/slk/internal/ui/themeswitcher/model.go", "source_location": "L198"}, {"caller_nid": "themeswitcher_model_renderbox", "callee": "Render", "is_member_call": true, "source_file": "/Users/siltala/dev/personal/slk/internal/ui/themeswitcher/model.go", "source_location": "L203"}, {"caller_nid": "themeswitcher_model_renderbox", "callee": "Foreground", "is_member_call": true, "source_file": "/Users/siltala/dev/personal/slk/internal/ui/themeswitcher/model.go", "source_location": "L203"}, {"caller_nid": "themeswitcher_model_renderbox", "callee": "Background", "is_member_call": true, "source_file": "/Users/siltala/dev/personal/slk/internal/ui/themeswitcher/model.go", "source_location": "L203"}, {"caller_nid": "themeswitcher_model_renderbox", "callee": "PaddingLeft", "is_member_call": true, "source_file": "/Users/siltala/dev/personal/slk/internal/ui/themeswitcher/model.go", "source_location": "L203"}, {"caller_nid": "themeswitcher_model_renderbox", "callee": "BorderBackground", "is_member_call": true, "source_file": "/Users/siltala/dev/personal/slk/internal/ui/themeswitcher/model.go", "source_location": "L203"}, {"caller_nid": "themeswitcher_model_renderbox", "callee": "BorderForeground", "is_member_call": true, "source_file": "/Users/siltala/dev/personal/slk/internal/ui/themeswitcher/model.go", "source_location": "L203"}, {"caller_nid": "themeswitcher_model_renderbox", "callee": "BorderLeft", "is_member_call": true, "source_file": "/Users/siltala/dev/personal/slk/internal/ui/themeswitcher/model.go", "source_location": "L203"}, {"caller_nid": "themeswitcher_model_renderbox", "callee": "BorderStyle", "is_member_call": true, "source_file": "/Users/siltala/dev/personal/slk/internal/ui/themeswitcher/model.go", "source_location": "L203"}, {"caller_nid": "themeswitcher_model_renderbox", "callee": "NewStyle", "is_member_call": true, "source_file": "/Users/siltala/dev/personal/slk/internal/ui/themeswitcher/model.go", "source_location": "L203"}, {"caller_nid": "themeswitcher_model_renderbox", "callee": "Foreground", "is_member_call": true, "source_file": "/Users/siltala/dev/personal/slk/internal/ui/themeswitcher/model.go", "source_location": "L265"}, {"caller_nid": "themeswitcher_model_renderbox", "callee": "Background", "is_member_call": true, "source_file": "/Users/siltala/dev/personal/slk/internal/ui/themeswitcher/model.go", "source_location": "L265"}, {"caller_nid": "themeswitcher_model_renderbox", "callee": "NewStyle", "is_member_call": true, "source_file": "/Users/siltala/dev/personal/slk/internal/ui/themeswitcher/model.go", "source_location": "L265"}, {"caller_nid": "themeswitcher_model_renderbox", "callee": "Foreground", "is_member_call": true, "source_file": "/Users/siltala/dev/personal/slk/internal/ui/themeswitcher/model.go", "source_location": "L266"}, {"caller_nid": "themeswitcher_model_renderbox", "callee": "Background", "is_member_call": true, "source_file": "/Users/siltala/dev/personal/slk/internal/ui/themeswitcher/model.go", "source_location": "L266"}, {"caller_nid": "themeswitcher_model_renderbox", "callee": "NewStyle", "is_member_call": true, "source_file": "/Users/siltala/dev/personal/slk/internal/ui/themeswitcher/model.go", "source_location": "L266"}, {"caller_nid": "themeswitcher_model_renderbox", "callee": "Width", "is_member_call": true, "source_file": "/Users/siltala/dev/personal/slk/internal/ui/themeswitcher/model.go", "source_location": "L273"}, {"caller_nid": "themeswitcher_model_renderbox", "callee": "StringWithTail", "is_member_call": false, "source_file": "/Users/siltala/dev/personal/slk/internal/ui/themeswitcher/model.go", "source_location": "L274"}, {"caller_nid": "themeswitcher_model_renderbox", "callee": "uint", "is_member_call": false, "source_file": "/Users/siltala/dev/personal/slk/internal/ui/themeswitcher/model.go", "source_location": "L274"}, {"caller_nid": "themeswitcher_model_renderbox", "callee": "Render", "is_member_call": true, "source_file": "/Users/siltala/dev/personal/slk/internal/ui/themeswitcher/model.go", "source_location": "L279"}, {"caller_nid": "themeswitcher_model_renderbox", "callee": "Foreground", "is_member_call": true, "source_file": "/Users/siltala/dev/personal/slk/internal/ui/themeswitcher/model.go", "source_location": "L279"}, {"caller_nid": "themeswitcher_model_renderbox", "callee": "Background", "is_member_call": true, "source_file": "/Users/siltala/dev/personal/slk/internal/ui/themeswitcher/model.go", "source_location": "L279"}, {"caller_nid": "themeswitcher_model_renderbox", "callee": "NewStyle", "is_member_call": true, "source_file": "/Users/siltala/dev/personal/slk/internal/ui/themeswitcher/model.go", "source_location": "L279"}, {"caller_nid": "themeswitcher_model_renderbox", "callee": "Render", "is_member_call": true, "source_file": "/Users/siltala/dev/personal/slk/internal/ui/themeswitcher/model.go", "source_location": "L280"}, {"caller_nid": "themeswitcher_model_renderbox", "callee": "Width", "is_member_call": true, "source_file": "/Users/siltala/dev/personal/slk/internal/ui/themeswitcher/model.go", "source_location": "L280"}, {"caller_nid": "themeswitcher_model_renderbox", "callee": "Bold", "is_member_call": true, "source_file": "/Users/siltala/dev/personal/slk/internal/ui/themeswitcher/model.go", "source_location": "L280"}, {"caller_nid": "themeswitcher_model_renderbox", "callee": "Foreground", "is_member_call": true, "source_file": "/Users/siltala/dev/personal/slk/internal/ui/themeswitcher/model.go", "source_location": "L280"}, {"caller_nid": "themeswitcher_model_renderbox", "callee": "Background", "is_member_call": true, "source_file": "/Users/siltala/dev/personal/slk/internal/ui/themeswitcher/model.go", "source_location": "L280"}, {"caller_nid": "themeswitcher_model_renderbox", "callee": "NewStyle", "is_member_call": true, "source_file": "/Users/siltala/dev/personal/slk/internal/ui/themeswitcher/model.go", "source_location": "L280"}, {"caller_nid": "themeswitcher_model_renderbox", "callee": "Render", "is_member_call": true, "source_file": "/Users/siltala/dev/personal/slk/internal/ui/themeswitcher/model.go", "source_location": "L288"}, {"caller_nid": "themeswitcher_model_renderbox", "callee": "Width", "is_member_call": true, "source_file": "/Users/siltala/dev/personal/slk/internal/ui/themeswitcher/model.go", "source_location": "L288"}, {"caller_nid": "themeswitcher_model_renderbox", "callee": "Foreground", "is_member_call": true, "source_file": "/Users/siltala/dev/personal/slk/internal/ui/themeswitcher/model.go", "source_location": "L288"}, {"caller_nid": "themeswitcher_model_renderbox", "callee": "Background", "is_member_call": true, "source_file": "/Users/siltala/dev/personal/slk/internal/ui/themeswitcher/model.go", "source_location": "L288"}, {"caller_nid": "themeswitcher_model_renderbox", "callee": "NewStyle", "is_member_call": true, "source_file": "/Users/siltala/dev/personal/slk/internal/ui/themeswitcher/model.go", "source_location": "L288"}, {"caller_nid": "themeswitcher_model_renderbox", "callee": "Render", "is_member_call": true, "source_file": "/Users/siltala/dev/personal/slk/internal/ui/themeswitcher/model.go", "source_location": "L300"}, {"caller_nid": "themeswitcher_model_renderbox", "callee": "Render", "is_member_call": true, "source_file": "/Users/siltala/dev/personal/slk/internal/ui/themeswitcher/model.go", "source_location": "L302"}, {"caller_nid": "themeswitcher_model_renderbox", "callee": "append", "is_member_call": false, "source_file": "/Users/siltala/dev/personal/slk/internal/ui/themeswitcher/model.go", "source_location": "L306"}, {"caller_nid": "themeswitcher_model_renderbox", "callee": "Render", "is_member_call": true, "source_file": "/Users/siltala/dev/personal/slk/internal/ui/themeswitcher/model.go", "source_location": "L310"}, {"caller_nid": "themeswitcher_model_renderbox", "callee": "Italic", "is_member_call": true, "source_file": "/Users/siltala/dev/personal/slk/internal/ui/themeswitcher/model.go", "source_location": "L310"}, {"caller_nid": "themeswitcher_model_renderbox", "callee": "Foreground", "is_member_call": true, "source_file": "/Users/siltala/dev/personal/slk/internal/ui/themeswitcher/model.go", "source_location": "L310"}, {"caller_nid": "themeswitcher_model_renderbox", "callee": "Background", "is_member_call": true, "source_file": "/Users/siltala/dev/personal/slk/internal/ui/themeswitcher/model.go", "source_location": "L310"}, {"caller_nid": "themeswitcher_model_renderbox", "callee": "NewStyle", "is_member_call": true, "source_file": "/Users/siltala/dev/personal/slk/internal/ui/themeswitcher/model.go", "source_location": "L310"}, {"caller_nid": "themeswitcher_model_renderbox", "callee": "append", "is_member_call": false, "source_file": "/Users/siltala/dev/personal/slk/internal/ui/themeswitcher/model.go", "source_location": "L315"}, {"caller_nid": "themeswitcher_model_renderbox", "callee": "Join", "is_member_call": false, "source_file": "/Users/siltala/dev/personal/slk/internal/ui/themeswitcher/model.go", "source_location": "L318"}, {"caller_nid": "themeswitcher_model_renderbox", "callee": "ReapplyBgAfterResets", "is_member_call": false, "source_file": "/Users/siltala/dev/personal/slk/internal/ui/themeswitcher/model.go", "source_location": "L322"}, {"caller_nid": "themeswitcher_model_renderbox", "callee": "BgANSI", "is_member_call": false, "source_file": "/Users/siltala/dev/personal/slk/internal/ui/themeswitcher/model.go", "source_location": "L322"}, {"caller_nid": "themeswitcher_model_renderbox", "callee": "FgANSI", "is_member_call": false, "source_file": "/Users/siltala/dev/personal/slk/internal/ui/themeswitcher/model.go", "source_location": "L322"}, {"caller_nid": "themeswitcher_model_renderbox", "callee": "Render", "is_member_call": true, "source_file": "/Users/siltala/dev/personal/slk/internal/ui/themeswitcher/model.go", "source_location": "L324"}, {"caller_nid": "themeswitcher_model_renderbox", "callee": "Width", "is_member_call": true, "source_file": "/Users/siltala/dev/personal/slk/internal/ui/themeswitcher/model.go", "source_location": "L324"}, {"caller_nid": "themeswitcher_model_renderbox", "callee": "Padding", "is_member_call": true, "source_file": "/Users/siltala/dev/personal/slk/internal/ui/themeswitcher/model.go", "source_location": "L324"}, {"caller_nid": "themeswitcher_model_renderbox", "callee": "Background", "is_member_call": true, "source_file": "/Users/siltala/dev/personal/slk/internal/ui/themeswitcher/model.go", "source_location": "L324"}, {"caller_nid": "themeswitcher_model_renderbox", "callee": "BorderBackground", "is_member_call": true, "source_file": "/Users/siltala/dev/personal/slk/internal/ui/themeswitcher/model.go", "source_location": "L324"}, {"caller_nid": "themeswitcher_model_renderbox", "callee": "BorderForeground", "is_member_call": true, "source_file": "/Users/siltala/dev/personal/slk/internal/ui/themeswitcher/model.go", "source_location": "L324"}, {"caller_nid": "themeswitcher_model_renderbox", "callee": "Border", "is_member_call": true, "source_file": "/Users/siltala/dev/personal/slk/internal/ui/themeswitcher/model.go", "source_location": "L324"}, {"caller_nid": "themeswitcher_model_renderbox", "callee": "NewStyle", "is_member_call": true, "source_file": "/Users/siltala/dev/personal/slk/internal/ui/themeswitcher/model.go", "source_location": "L324"}, {"caller_nid": "themeswitcher_model_renderbox", "callee": "RoundedBorder", "is_member_call": true, "source_file": "/Users/siltala/dev/personal/slk/internal/ui/themeswitcher/model.go", "source_location": "L325"}]}