{"nodes": [{"id": "users_siltala_dev_personal_slk_internal_ui_styles_tint_go", "label": "tint.go", "file_type": "code", "source_file": "internal/ui/styles/tint.go", "source_location": "L1"}, {"id": "styles_tint_selectiontintcolor", "label": "SelectionTintColor()", "file_type": "code", "source_file": "internal/ui/styles/tint.go", "source_location": "L36"}, {"id": "color", "label": "Color", "file_type": "code", "source_file": "internal/ui/styles/tint.go", "source_location": "L36"}, {"id": "styles_tint_mixcolors", "label": "mixColors()", "file_type": "code", "source_file": "internal/ui/styles/tint.go", "source_location": "L51"}, {"id": "styles_tint_rgbhex", "label": "rgbHex()", "file_type": "code", "source_file": "internal/ui/styles/tint.go", "source_location": "L69"}, {"id": "styles_tint_resetderivedtints", "label": "resetDerivedTints()", "file_type": "code", "source_file": "internal/ui/styles/tint.go", "source_location": "L84"}], "edges": [{"source": "users_siltala_dev_personal_slk_internal_ui_styles_tint_go", "target": "go_pkg_image_color", "relation": "imports_from", "confidence": "EXTRACTED", "source_file": "internal/ui/styles/tint.go", "source_location": "L5", "weight": 1.0, "context": "import"}, {"source": "users_siltala_dev_personal_slk_internal_ui_styles_tint_go", "target": "go_pkg_math", "relation": "imports_from", "confidence": "EXTRACTED", "source_file": "internal/ui/styles/tint.go", "source_location": "L6", "weight": 1.0, "context": "import"}, {"source": "users_siltala_dev_personal_slk_internal_ui_styles_tint_go", "target": "go_pkg_charm_land_lipgloss_v2", "relation": "imports_from", "confidence": "EXTRACTED", "source_file": "internal/ui/styles/tint.go", "source_location": "L8", "weight": 1.0, "context": "import"}, {"source": "users_siltala_dev_personal_slk_internal_ui_styles_tint_go", "target": "styles_tint_selectiontintcolor", "relation": "contains", "confidence": "EXTRACTED", "source_file": "internal/ui/styles/tint.go", "source_location": "L36", "weight": 1.0}, {"source": "styles_tint_selectiontintcolor", "target": "color", "relation": "references", "confidence": "EXTRACTED", "source_file": "internal/ui/styles/tint.go", "source_location": "L36", "weight": 1.0, "context": "return_type"}, {"source": "users_siltala_dev_personal_slk_internal_ui_styles_tint_go", "target": "styles_tint_mixcolors", "relation": "contains", "confidence": "EXTRACTED", "source_file": "internal/ui/styles/tint.go", "source_location": "L51", "weight": 1.0}, {"source": "styles_tint_mixcolors", "target": "color", "relation": "references", "confidence": "EXTRACTED", "source_file": "internal/ui/styles/tint.go", "source_location": "L51", "weight": 1.0, "context": "parameter_type"}, {"source": "styles_tint_mixcolors", "target": "color", "relation": "references", "confidence": "EXTRACTED", "source_file": "internal/ui/styles/tint.go", "source_location": "L51", "weight": 1.0, "context": "return_type"}, {"source": "users_siltala_dev_personal_slk_internal_ui_styles_tint_go", "target": "styles_tint_rgbhex", "relation": "contains", "confidence": "EXTRACTED", "source_file": "internal/ui/styles/tint.go", "source_location": "L69", "weight": 1.0}, {"source": "users_siltala_dev_personal_slk_internal_ui_styles_tint_go", "target": "styles_tint_resetderivedtints", "relation": "contains", "confidence": "EXTRACTED", "source_file": "internal/ui/styles/tint.go", "source_location": "L84", "weight": 1.0}, {"source": "styles_tint_selectiontintcolor", "target": "styles_tint_mixcolors", "relation": "calls", "context": "call", "confidence": "EXTRACTED", "source_file": "internal/ui/styles/tint.go", "source_location": "L39", "weight": 1.0}, {"source": "styles_tint_mixcolors", "target": "color", "relation": "calls", "context": "call", "confidence": "EXTRACTED", "source_file": "internal/ui/styles/tint.go", "source_location": "L66", "weight": 1.0}, {"source": "styles_tint_mixcolors", "target": "styles_tint_rgbhex", "relation": "calls", "context": "call", "confidence": "EXTRACTED", "source_file": "internal/ui/styles/tint.go", "source_location": "L66", "weight": 1.0}], "raw_calls": [{"caller_nid": "styles_tint_mixcolors", "callee": "RGBA", "is_member_call": true, "source_file": "/Users/siltala/dev/personal/slk/internal/ui/styles/tint.go", "source_location": "L58"}, {"caller_nid": "styles_tint_mixcolors", "callee": "RGBA", "is_member_call": true, "source_file": "/Users/siltala/dev/personal/slk/internal/ui/styles/tint.go", "source_location": "L59"}, {"caller_nid": "styles_tint_mixcolors", "callee": "float64", "is_member_call": false, "source_file": "/Users/siltala/dev/personal/slk/internal/ui/styles/tint.go", "source_location": "L61"}, {"caller_nid": "styles_tint_mixcolors", "callee": "float64", "is_member_call": false, "source_file": "/Users/siltala/dev/personal/slk/internal/ui/styles/tint.go", "source_location": "L61"}, {"caller_nid": "styles_tint_mixcolors", "callee": "float64", "is_member_call": false, "source_file": "/Users/siltala/dev/personal/slk/internal/ui/styles/tint.go", "source_location": "L61"}, {"caller_nid": "styles_tint_mixcolors", "callee": "float64", "is_member_call": false, "source_file": "/Users/siltala/dev/personal/slk/internal/ui/styles/tint.go", "source_location": "L62"}, {"caller_nid": "styles_tint_mixcolors", "callee": "float64", "is_member_call": false, "source_file": "/Users/siltala/dev/personal/slk/internal/ui/styles/tint.go", "source_location": "L62"}, {"caller_nid": "styles_tint_mixcolors", "callee": "float64", "is_member_call": false, "source_file": "/Users/siltala/dev/personal/slk/internal/ui/styles/tint.go", "source_location": "L62"}, {"caller_nid": "styles_tint_mixcolors", "callee": "uint8", "is_member_call": false, "source_file": "/Users/siltala/dev/personal/slk/internal/ui/styles/tint.go", "source_location": "L63"}, {"caller_nid": "styles_tint_mixcolors", "callee": "Round", "is_member_call": false, "source_file": "/Users/siltala/dev/personal/slk/internal/ui/styles/tint.go", "source_location": "L63"}, {"caller_nid": "styles_tint_mixcolors", "callee": "uint8", "is_member_call": false, "source_file": "/Users/siltala/dev/personal/slk/internal/ui/styles/tint.go", "source_location": "L64"}, {"caller_nid": "styles_tint_mixcolors", "callee": "Round", "is_member_call": false, "source_file": "/Users/siltala/dev/personal/slk/internal/ui/styles/tint.go", "source_location": "L64"}, {"caller_nid": "styles_tint_mixcolors", "callee": "uint8", "is_member_call": false, "source_file": "/Users/siltala/dev/personal/slk/internal/ui/styles/tint.go", "source_location": "L65"}, {"caller_nid": "styles_tint_mixcolors", "callee": "Round", "is_member_call": false, "source_file": "/Users/siltala/dev/personal/slk/internal/ui/styles/tint.go", "source_location": "L65"}, {"caller_nid": "styles_tint_rgbhex", "callee": "string", "is_member_call": false, "source_file": "/Users/siltala/dev/personal/slk/internal/ui/styles/tint.go", "source_location": "L78"}]}