{"nodes": [{"id": "users_siltala_dev_personal_slk_internal_ui_messages_render_go", "label": "render.go", "file_type": "code", "source_file": "internal/ui/messages/render.go", "source_location": "L1"}, {"id": "messages_render_boldstyle", "label": "boldStyle()", "file_type": "code", "source_file": "internal/ui/messages/render.go", "source_location": "L86"}, {"id": "style", "label": "Style", "file_type": "code", "source_file": "internal/ui/messages/render.go", "source_location": "L86"}, {"id": "messages_render_italicstyle", "label": "italicStyle()", "file_type": "code", "source_file": "internal/ui/messages/render.go", "source_location": "L89"}, {"id": "messages_render_strikethroughstyle", "label": "strikethroughStyle()", "file_type": "code", "source_file": "internal/ui/messages/render.go", "source_location": "L92"}, {"id": "messages_render_codestyle", "label": "codeStyle()", "file_type": "code", "source_file": "internal/ui/messages/render.go", "source_location": "L95"}, {"id": "messages_render_codeblockstyle", "label": "codeBlockStyle()", "file_type": "code", "source_file": "internal/ui/messages/render.go", "source_location": "L100"}, {"id": "messages_render_linkstyle", "label": "linkStyle()", "file_type": "code", "source_file": "internal/ui/messages/render.go", "source_location": "L106"}, {"id": "messages_render_mentionstyle", "label": "mentionStyle()", "file_type": "code", "source_file": "internal/ui/messages/render.go", "source_location": "L111"}, {"id": "messages_render_blockquotestyle", "label": "blockquoteStyle()", "file_type": "code", "source_file": "internal/ui/messages/render.go", "source_location": "L116"}, {"id": "messages_render_renderattachments", "label": "RenderAttachments()", "file_type": "code", "source_file": "internal/ui/messages/render.go", "source_location": "L141"}, {"id": "attachment", "label": "Attachment", "file_type": "code", "source_file": "internal/ui/messages/render.go", "source_location": "L141"}, {"id": "messages_render_rendersingleattachment", "label": "renderSingleAttachment()", "file_type": "code", "source_file": "internal/ui/messages/render.go", "source_location": "L157"}, {"id": "messages_render_osc8hyperlink", "label": "osc8Hyperlink()", "file_type": "code", "source_file": "internal/ui/messages/render.go", "source_location": "L177"}, {"id": "messages_render_wordwrap", "label": "WordWrap()", "file_type": "code", "source_file": "internal/ui/messages/render.go", "source_location": "L189"}, {"id": "messages_render_wrapline", "label": "wrapLine()", "file_type": "code", "source_file": "internal/ui/messages/render.go", "source_location": "L209"}, {"id": "builder", "label": "Builder", "file_type": "code", "source_file": "internal/ui/messages/render.go", "source_location": "L209"}, {"id": "messages_render_reapplybgafterresets", "label": "ReapplyBgAfterResets()", "file_type": "code", "source_file": "internal/ui/messages/render.go", "source_location": "L264"}, {"id": "messages_render_selectiontintbgansi", "label": "SelectionTintBgANSI()", "file_type": "code", "source_file": "internal/ui/messages/render.go", "source_location": "L299"}, {"id": "messages_render_repaintbgtoselectiontint", "label": "RepaintBgToSelectionTint()", "file_type": "code", "source_file": "internal/ui/messages/render.go", "source_location": "L339"}, {"id": "messages_render_bgsgrparams", "label": "bgSGRParams()", "file_type": "code", "source_file": "internal/ui/messages/render.go", "source_location": "L351"}, {"id": "messages_render_substitutebgsgr", "label": "substituteBgSGR()", "file_type": "code", "source_file": "internal/ui/messages/render.go", "source_location": "L373"}, {"id": "messages_sgrparam", "label": "sgrParam", "file_type": "code", "source_file": "internal/ui/messages/render.go", "source_location": "L430"}, {"id": "messages_render_splitsgrparams", "label": "splitSGRParams()", "file_type": "code", "source_file": "internal/ui/messages/render.go", "source_location": "L438"}, {"id": "messages_render_isbasicbgparam", "label": "isBasicBgParam()", "file_type": "code", "source_file": "internal/ui/messages/render.go", "source_location": "L486"}, {"id": "messages_render_bgansifor", "label": "bgANSIFor()", "file_type": "code", "source_file": "internal/ui/messages/render.go", "source_location": "L500"}, {"id": "color", "label": "Color", "file_type": "code", "source_file": "internal/ui/messages/render.go", "source_location": "L500"}, {"id": "messages_render_fgansifor", "label": "fgANSIFor()", "file_type": "code", "source_file": "internal/ui/messages/render.go", "source_location": "L519"}, {"id": "messages_render_bgansi", "label": "BgANSI()", "file_type": "code", "source_file": "internal/ui/messages/render.go", "source_location": "L538"}, {"id": "messages_render_sidebarbgansi", "label": "SidebarBgANSI()", "file_type": "code", "source_file": "internal/ui/messages/render.go", "source_location": "L554"}, {"id": "messages_render_fgansi", "label": "FgANSI()", "file_type": "code", "source_file": "internal/ui/messages/render.go", "source_location": "L569"}, {"id": "messages_render_sidebarfgansi", "label": "SidebarFgANSI()", "file_type": "code", "source_file": "internal/ui/messages/render.go", "source_location": "L580"}, {"id": "messages_render_sidebarmutedfgansi", "label": "SidebarMutedFgANSI()", "file_type": "code", "source_file": "internal/ui/messages/render.go", "source_location": "L598"}, {"id": "messages_renderslackmarkdownopts", "label": "RenderSlackMarkdownOpts", "file_type": "code", "source_file": "internal/ui/messages/render.go", "source_location": "L618"}, {"id": "placecontext", "label": "PlaceContext", "file_type": "code", "source_file": "internal/ui/messages/render.go", "source_location": "L624"}, {"id": "writer", "label": "Writer", "file_type": "code", "source_file": "internal/ui/messages/render.go", "source_location": "L627"}, {"id": "messages_render_renderslackmarkdown", "label": "RenderSlackMarkdown()", "file_type": "code", "source_file": "internal/ui/messages/render.go", "source_location": "L641"}, {"id": "messages_render_renderslackmarkdownwith", "label": "RenderSlackMarkdownWith()", "file_type": "code", "source_file": "internal/ui/messages/render.go", "source_location": "L651"}, {"id": "messages_render_renderinlineformattingwith", "label": "renderInlineFormattingWith()", "file_type": "code", "source_file": "internal/ui/messages/render.go", "source_location": "L691"}, {"id": "messages_render_renderemojitokensinline", "label": "renderEmojiTokensInline()", "file_type": "code", "source_file": "internal/ui/messages/render.go", "source_location": "L837"}, {"id": "token", "label": "Token", "file_type": "code", "source_file": "internal/ui/messages/render.go", "source_location": "L837"}, {"id": "messages_render_slackmrkdwntocommonmark", "label": "SlackMrkdwnToCommonMark()", "file_type": "code", "source_file": "internal/ui/messages/render.go", "source_location": "L876"}, {"id": "messages_render_slackmrkdwntocommonmarkinline", "label": "slackMrkdwnToCommonMarkInline()", "file_type": "code", "source_file": "internal/ui/messages/render.go", "source_location": "L927"}, {"id": "messages_render_resolveshortcodescommonmark", "label": "resolveShortcodesCommonMark()", "file_type": "code", "source_file": "internal/ui/messages/render.go", "source_location": "L979"}, {"id": "messages_render_renderitalics", "label": "renderItalics()", "file_type": "code", "source_file": "internal/ui/messages/render.go", "source_location": "L999"}, {"id": "messages_render_isitalicwordrune", "label": "isItalicWordRune()", "file_type": "code", "source_file": "internal/ui/messages/render.go", "source_location": "L1049"}, {"id": "messages_plainline", "label": "plainLine", "file_type": "code", "source_file": "internal/ui/messages/render.go", "source_location": "L1076"}, {"id": "messages_render_plainlines", "label": "plainLines()", "file_type": "code", "source_file": "internal/ui/messages/render.go", "source_location": "L1090"}, {"id": "messages_render_buildplainline", "label": "buildPlainLine()", "file_type": "code", "source_file": "internal/ui/messages/render.go", "source_location": "L1103"}, {"id": "messages_render_displaywidthofplain", "label": "displayWidthOfPlain()", "file_type": "code", "source_file": "internal/ui/messages/render.go", "source_location": "L1136"}, {"id": "messages_render_slicecolumns", "label": "sliceColumns()", "file_type": "code", "source_file": "internal/ui/messages/render.go", "source_location": "L1148"}], "edges": [{"source": "users_siltala_dev_personal_slk_internal_ui_messages_render_go", "target": "go_pkg_fmt", "relation": "imports_from", "confidence": "EXTRACTED", "source_file": "internal/ui/messages/render.go", "source_location": "L4", "weight": 1.0, "context": "import"}, {"source": "users_siltala_dev_personal_slk_internal_ui_messages_render_go", "target": "go_pkg_image_color", "relation": "imports_from", "confidence": "EXTRACTED", "source_file": "internal/ui/messages/render.go", "source_location": "L5", "weight": 1.0, "context": "import"}, {"source": "users_siltala_dev_personal_slk_internal_ui_messages_render_go", "target": "go_pkg_io", "relation": "imports_from", "confidence": "EXTRACTED", "source_file": "internal/ui/messages/render.go", "source_location": "L6", "weight": 1.0, "context": "import"}, {"source": "users_siltala_dev_personal_slk_internal_ui_messages_render_go", "target": "go_pkg_regexp", "relation": "imports_from", "confidence": "EXTRACTED", "source_file": "internal/ui/messages/render.go", "source_location": "L7", "weight": 1.0, "context": "import"}, {"source": "users_siltala_dev_personal_slk_internal_ui_messages_render_go", "target": "go_pkg_strings", "relation": "imports_from", "confidence": "EXTRACTED", "source_file": "internal/ui/messages/render.go", "source_location": "L8", "weight": 1.0, "context": "import"}, {"source": "users_siltala_dev_personal_slk_internal_ui_messages_render_go", "target": "go_pkg_unicode", "relation": "imports_from", "confidence": "EXTRACTED", "source_file": "internal/ui/messages/render.go", "source_location": "L9", "weight": 1.0, "context": "import"}, {"source": "users_siltala_dev_personal_slk_internal_ui_messages_render_go", "target": "go_pkg_charm_land_lipgloss_v2", "relation": "imports_from", "confidence": "EXTRACTED", "source_file": "internal/ui/messages/render.go", "source_location": "L11", "weight": 1.0, "context": "import"}, {"source": "users_siltala_dev_personal_slk_internal_ui_messages_render_go", "target": "go_pkg_github_com_charmbracelet_x_ansi", "relation": "imports_from", "confidence": "EXTRACTED", "source_file": "internal/ui/messages/render.go", "source_location": "L12", "weight": 1.0, "context": "import"}, {"source": "users_siltala_dev_personal_slk_internal_ui_messages_render_go", "target": "go_pkg_github_com_gammons_slk_internal_emoji", "relation": "imports_from", "confidence": "EXTRACTED", "source_file": "internal/ui/messages/render.go", "source_location": "L13", "weight": 1.0, "context": "import"}, {"source": "users_siltala_dev_personal_slk_internal_ui_messages_render_go", "target": "go_pkg_github_com_gammons_slk_internal_ui_styles", "relation": "imports_from", "confidence": "EXTRACTED", "source_file": "internal/ui/messages/render.go", "source_location": "L14", "weight": 1.0, "context": "import"}, {"source": "users_siltala_dev_personal_slk_internal_ui_messages_render_go", "target": "go_pkg_github_com_kyokomi_emoji_v2", "relation": "imports_from", "confidence": "EXTRACTED", "source_file": "internal/ui/messages/render.go", "source_location": "L15", "weight": 1.0, "context": "import"}, {"source": "users_siltala_dev_personal_slk_internal_ui_messages_render_go", "target": "go_pkg_github_com_rivo_uniseg", "relation": "imports_from", "confidence": "EXTRACTED", "source_file": "internal/ui/messages/render.go", "source_location": "L16", "weight": 1.0, "context": "import"}, {"source": "users_siltala_dev_personal_slk_internal_ui_messages_render_go", "target": "messages_render_boldstyle", "relation": "contains", "confidence": "EXTRACTED", "source_file": "internal/ui/messages/render.go", "source_location": "L86", "weight": 1.0}, {"source": "messages_render_boldstyle", "target": "style", "relation": "references", "confidence": "EXTRACTED", "source_file": "internal/ui/messages/render.go", "source_location": "L86", "weight": 1.0, "context": "return_type"}, {"source": "users_siltala_dev_personal_slk_internal_ui_messages_render_go", "target": "messages_render_italicstyle", "relation": "contains", "confidence": "EXTRACTED", "source_file": "internal/ui/messages/render.go", "source_location": "L89", "weight": 1.0}, {"source": "messages_render_italicstyle", "target": "style", "relation": "references", "confidence": "EXTRACTED", "source_file": "internal/ui/messages/render.go", "source_location": "L89", "weight": 1.0, "context": "return_type"}, {"source": "users_siltala_dev_personal_slk_internal_ui_messages_render_go", "target": "messages_render_strikethroughstyle", "relation": "contains", "confidence": "EXTRACTED", "source_file": "internal/ui/messages/render.go", "source_location": "L92", "weight": 1.0}, {"source": "messages_render_strikethroughstyle", "target": "style", "relation": "references", "confidence": "EXTRACTED", "source_file": "internal/ui/messages/render.go", "source_location": "L92", "weight": 1.0, "context": "return_type"}, {"source": "users_siltala_dev_personal_slk_internal_ui_messages_render_go", "target": "messages_render_codestyle", "relation": "contains", "confidence": "EXTRACTED", "source_file": "internal/ui/messages/render.go", "source_location": "L95", "weight": 1.0}, {"source": "messages_render_codestyle", "target": "style", "relation": "references", "confidence": "EXTRACTED", "source_file": "internal/ui/messages/render.go", "source_location": "L95", "weight": 1.0, "context": "return_type"}, {"source": "users_siltala_dev_personal_slk_internal_ui_messages_render_go", "target": "messages_render_codeblockstyle", "relation": "contains", "confidence": "EXTRACTED", "source_file": "internal/ui/messages/render.go", "source_location": "L100", "weight": 1.0}, {"source": "messages_render_codeblockstyle", "target": "style", "relation": "references", "confidence": "EXTRACTED", "source_file": "internal/ui/messages/render.go", "source_location": "L100", "weight": 1.0, "context": "return_type"}, {"source": "users_siltala_dev_personal_slk_internal_ui_messages_render_go", "target": "messages_render_linkstyle", "relation": "contains", "confidence": "EXTRACTED", "source_file": "internal/ui/messages/render.go", "source_location": "L106", "weight": 1.0}, {"source": "messages_render_linkstyle", "target": "style", "relation": "references", "confidence": "EXTRACTED", "source_file": "internal/ui/messages/render.go", "source_location": "L106", "weight": 1.0, "context": "return_type"}, {"source": "users_siltala_dev_personal_slk_internal_ui_messages_render_go", "target": "messages_render_mentionstyle", "relation": "contains", "confidence": "EXTRACTED", "source_file": "internal/ui/messages/render.go", "source_location": "L111", "weight": 1.0}, {"source": "messages_render_mentionstyle", "target": "style", "relation": "references", "confidence": "EXTRACTED", "source_file": "internal/ui/messages/render.go", "source_location": "L111", "weight": 1.0, "context": "return_type"}, {"source": "users_siltala_dev_personal_slk_internal_ui_messages_render_go", "target": "messages_render_blockquotestyle", "relation": "contains", "confidence": "EXTRACTED", "source_file": "internal/ui/messages/render.go", "source_location": "L116", "weight": 1.0}, {"source": "messages_render_blockquotestyle", "target": "style", "relation": "references", "confidence": "EXTRACTED", "source_file": "internal/ui/messages/render.go", "source_location": "L116", "weight": 1.0, "context": "return_type"}, {"source": "users_siltala_dev_personal_slk_internal_ui_messages_render_go", "target": "messages_render_renderattachments", "relation": "contains", "confidence": "EXTRACTED", "source_file": "internal/ui/messages/render.go", "source_location": "L141", "weight": 1.0}, {"source": "messages_render_renderattachments", "target": "attachment", "relation": "references", "confidence": "EXTRACTED", "source_file": "internal/ui/messages/render.go", "source_location": "L141", "weight": 1.0, "context": "parameter_type"}, {"source": "users_siltala_dev_personal_slk_internal_ui_messages_render_go", "target": "messages_render_rendersingleattachment", "relation": "contains", "confidence": "EXTRACTED", "source_file": "internal/ui/messages/render.go", "source_location": "L157", "weight": 1.0}, {"source": "messages_render_rendersingleattachment", "target": "attachment", "relation": "references", "confidence": "EXTRACTED", "source_file": "internal/ui/messages/render.go", "source_location": "L157", "weight": 1.0, "context": "parameter_type"}, {"source": "users_siltala_dev_personal_slk_internal_ui_messages_render_go", "target": "messages_render_osc8hyperlink", "relation": "contains", "confidence": "EXTRACTED", "source_file": "internal/ui/messages/render.go", "source_location": "L177", "weight": 1.0}, {"source": "users_siltala_dev_personal_slk_internal_ui_messages_render_go", "target": "messages_render_wordwrap", "relation": "contains", "confidence": "EXTRACTED", "source_file": "internal/ui/messages/render.go", "source_location": "L189", "weight": 1.0}, {"source": "users_siltala_dev_personal_slk_internal_ui_messages_render_go", "target": "messages_render_wrapline", "relation": "contains", "confidence": "EXTRACTED", "source_file": "internal/ui/messages/render.go", "source_location": "L209", "weight": 1.0}, {"source": "messages_render_wrapline", "target": "builder", "relation": "references", "confidence": "EXTRACTED", "source_file": "internal/ui/messages/render.go", "source_location": "L209", "weight": 1.0, "context": "parameter_type"}, {"source": "users_siltala_dev_personal_slk_internal_ui_messages_render_go", "target": "messages_render_reapplybgafterresets", "relation": "contains", "confidence": "EXTRACTED", "source_file": "internal/ui/messages/render.go", "source_location": "L264", "weight": 1.0}, {"source": "users_siltala_dev_personal_slk_internal_ui_messages_render_go", "target": "messages_render_selectiontintbgansi", "relation": "contains", "confidence": "EXTRACTED", "source_file": "internal/ui/messages/render.go", "source_location": "L299", "weight": 1.0}, {"source": "users_siltala_dev_personal_slk_internal_ui_messages_render_go", "target": "messages_render_repaintbgtoselectiontint", "relation": "contains", "confidence": "EXTRACTED", "source_file": "internal/ui/messages/render.go", "source_location": "L339", "weight": 1.0}, {"source": "users_siltala_dev_personal_slk_internal_ui_messages_render_go", "target": "messages_render_bgsgrparams", "relation": "contains", "confidence": "EXTRACTED", "source_file": "internal/ui/messages/render.go", "source_location": "L351", "weight": 1.0}, {"source": "users_siltala_dev_personal_slk_internal_ui_messages_render_go", "target": "messages_render_substitutebgsgr", "relation": "contains", "confidence": "EXTRACTED", "source_file": "internal/ui/messages/render.go", "source_location": "L373", "weight": 1.0}, {"source": "users_siltala_dev_personal_slk_internal_ui_messages_render_go", "target": "messages_sgrparam", "relation": "contains", "confidence": "EXTRACTED", "source_file": "internal/ui/messages/render.go", "source_location": "L430", "weight": 1.0}, {"source": "users_siltala_dev_personal_slk_internal_ui_messages_render_go", "target": "messages_render_splitsgrparams", "relation": "contains", "confidence": "EXTRACTED", "source_file": "internal/ui/messages/render.go", "source_location": "L438", "weight": 1.0}, {"source": "messages_render_splitsgrparams", "target": "messages_sgrparam", "relation": "references", "confidence": "EXTRACTED", "source_file": "internal/ui/messages/render.go", "source_location": "L438", "weight": 1.0, "context": "return_type"}, {"source": "users_siltala_dev_personal_slk_internal_ui_messages_render_go", "target": "messages_render_isbasicbgparam", "relation": "contains", "confidence": "EXTRACTED", "source_file": "internal/ui/messages/render.go", "source_location": "L486", "weight": 1.0}, {"source": "users_siltala_dev_personal_slk_internal_ui_messages_render_go", "target": "messages_render_bgansifor", "relation": "contains", "confidence": "EXTRACTED", "source_file": "internal/ui/messages/render.go", "source_location": "L500", "weight": 1.0}, {"source": "messages_render_bgansifor", "target": "color", "relation": "references", "confidence": "EXTRACTED", "source_file": "internal/ui/messages/render.go", "source_location": "L500", "weight": 1.0, "context": "parameter_type"}, {"source": "users_siltala_dev_personal_slk_internal_ui_messages_render_go", "target": "messages_render_fgansifor", "relation": "contains", "confidence": "EXTRACTED", "source_file": "internal/ui/messages/render.go", "source_location": "L519", "weight": 1.0}, {"source": "messages_render_fgansifor", "target": "color", "relation": "references", "confidence": "EXTRACTED", "source_file": "internal/ui/messages/render.go", "source_location": "L519", "weight": 1.0, "context": "parameter_type"}, {"source": "users_siltala_dev_personal_slk_internal_ui_messages_render_go", "target": "messages_render_bgansi", "relation": "contains", "confidence": "EXTRACTED", "source_file": "internal/ui/messages/render.go", "source_location": "L538", "weight": 1.0}, {"source": "users_siltala_dev_personal_slk_internal_ui_messages_render_go", "target": "messages_render_sidebarbgansi", "relation": "contains", "confidence": "EXTRACTED", "source_file": "internal/ui/messages/render.go", "source_location": "L554", "weight": 1.0}, {"source": "users_siltala_dev_personal_slk_internal_ui_messages_render_go", "target": "messages_render_fgansi", "relation": "contains", "confidence": "EXTRACTED", "source_file": "internal/ui/messages/render.go", "source_location": "L569", "weight": 1.0}, {"source": "users_siltala_dev_personal_slk_internal_ui_messages_render_go", "target": "messages_render_sidebarfgansi", "relation": "contains", "confidence": "EXTRACTED", "source_file": "internal/ui/messages/render.go", "source_location": "L580", "weight": 1.0}, {"source": "users_siltala_dev_personal_slk_internal_ui_messages_render_go", "target": "messages_render_sidebarmutedfgansi", "relation": "contains", "confidence": "EXTRACTED", "source_file": "internal/ui/messages/render.go", "source_location": "L598", "weight": 1.0}, {"source": "users_siltala_dev_personal_slk_internal_ui_messages_render_go", "target": "messages_renderslackmarkdownopts", "relation": "contains", "confidence": "EXTRACTED", "source_file": "internal/ui/messages/render.go", "source_location": "L618", "weight": 1.0}, {"source": "messages_renderslackmarkdownopts", "target": "placecontext", "relation": "references", "confidence": "EXTRACTED", "source_file": "internal/ui/messages/render.go", "source_location": "L624", "weight": 1.0, "context": "field"}, {"source": "messages_renderslackmarkdownopts", "target": "writer", "relation": "references", "confidence": "EXTRACTED", "source_file": "internal/ui/messages/render.go", "source_location": "L627", "weight": 1.0, "context": "field"}, {"source": "users_siltala_dev_personal_slk_internal_ui_messages_render_go", "target": "messages_render_renderslackmarkdown", "relation": "contains", "confidence": "EXTRACTED", "source_file": "internal/ui/messages/render.go", "source_location": "L641", "weight": 1.0}, {"source": "users_siltala_dev_personal_slk_internal_ui_messages_render_go", "target": "messages_render_renderslackmarkdownwith", "relation": "contains", "confidence": "EXTRACTED", "source_file": "internal/ui/messages/render.go", "source_location": "L651", "weight": 1.0}, {"source": "messages_render_renderslackmarkdownwith", "target": "messages_renderslackmarkdownopts", "relation": "references", "confidence": "EXTRACTED", "source_file": "internal/ui/messages/render.go", "source_location": "L651", "weight": 1.0, "context": "parameter_type"}, {"source": "users_siltala_dev_personal_slk_internal_ui_messages_render_go", "target": "messages_render_renderinlineformattingwith", "relation": "contains", "confidence": "EXTRACTED", "source_file": "internal/ui/messages/render.go", "source_location": "L691", "weight": 1.0}, {"source": "messages_render_renderinlineformattingwith", "target": "messages_renderslackmarkdownopts", "relation": "references", "confidence": "EXTRACTED", "source_file": "internal/ui/messages/render.go", "source_location": "L691", "weight": 1.0, "context": "parameter_type"}, {"source": "users_siltala_dev_personal_slk_internal_ui_messages_render_go", "target": "messages_render_renderemojitokensinline", "relation": "contains", "confidence": "EXTRACTED", "source_file": "internal/ui/messages/render.go", "source_location": "L837", "weight": 1.0}, {"source": "messages_render_renderemojitokensinline", "target": "token", "relation": "references", "confidence": "EXTRACTED", "source_file": "internal/ui/messages/render.go", "source_location": "L837", "weight": 1.0, "context": "parameter_type"}, {"source": "messages_render_renderemojitokensinline", "target": "placecontext", "relation": "references", "confidence": "EXTRACTED", "source_file": "internal/ui/messages/render.go", "source_location": "L837", "weight": 1.0, "context": "parameter_type"}, {"source": "messages_render_renderemojitokensinline", "target": "writer", "relation": "references", "confidence": "EXTRACTED", "source_file": "internal/ui/messages/render.go", "source_location": "L837", "weight": 1.0, "context": "parameter_type"}, {"source": "users_siltala_dev_personal_slk_internal_ui_messages_render_go", "target": "messages_render_slackmrkdwntocommonmark", "relation": "contains", "confidence": "EXTRACTED", "source_file": "internal/ui/messages/render.go", "source_location": "L876", "weight": 1.0}, {"source": "users_siltala_dev_personal_slk_internal_ui_messages_render_go", "target": "messages_render_slackmrkdwntocommonmarkinline", "relation": "contains", "confidence": "EXTRACTED", "source_file": "internal/ui/messages/render.go", "source_location": "L927", "weight": 1.0}, {"source": "users_siltala_dev_personal_slk_internal_ui_messages_render_go", "target": "messages_render_resolveshortcodescommonmark", "relation": "contains", "confidence": "EXTRACTED", "source_file": "internal/ui/messages/render.go", "source_location": "L979", "weight": 1.0}, {"source": "users_siltala_dev_personal_slk_internal_ui_messages_render_go", "target": "messages_render_renderitalics", "relation": "contains", "confidence": "EXTRACTED", "source_file": "internal/ui/messages/render.go", "source_location": "L999", "weight": 1.0}, {"source": "users_siltala_dev_personal_slk_internal_ui_messages_render_go", "target": "messages_render_isitalicwordrune", "relation": "contains", "confidence": "EXTRACTED", "source_file": "internal/ui/messages/render.go", "source_location": "L1049", "weight": 1.0}, {"source": "users_siltala_dev_personal_slk_internal_ui_messages_render_go", "target": "messages_plainline", "relation": "contains", "confidence": "EXTRACTED", "source_file": "internal/ui/messages/render.go", "source_location": "L1076", "weight": 1.0}, {"source": "users_siltala_dev_personal_slk_internal_ui_messages_render_go", "target": "messages_render_plainlines", "relation": "contains", "confidence": "EXTRACTED", "source_file": "internal/ui/messages/render.go", "source_location": "L1090", "weight": 1.0}, {"source": "messages_render_plainlines", "target": "messages_plainline", "relation": "references", "confidence": "EXTRACTED", "source_file": "internal/ui/messages/render.go", "source_location": "L1090", "weight": 1.0, "context": "return_type"}, {"source": "users_siltala_dev_personal_slk_internal_ui_messages_render_go", "target": "messages_render_buildplainline", "relation": "contains", "confidence": "EXTRACTED", "source_file": "internal/ui/messages/render.go", "source_location": "L1103", "weight": 1.0}, {"source": "messages_render_buildplainline", "target": "messages_plainline", "relation": "references", "confidence": "EXTRACTED", "source_file": "internal/ui/messages/render.go", "source_location": "L1103", "weight": 1.0, "context": "return_type"}, {"source": "users_siltala_dev_personal_slk_internal_ui_messages_render_go", "target": "messages_render_displaywidthofplain", "relation": "contains", "confidence": "EXTRACTED", "source_file": "internal/ui/messages/render.go", "source_location": "L1136", "weight": 1.0}, {"source": "messages_render_displaywidthofplain", "target": "messages_plainline", "relation": "references", "confidence": "EXTRACTED", "source_file": "internal/ui/messages/render.go", "source_location": "L1136", "weight": 1.0, "context": "parameter_type"}, {"source": "users_siltala_dev_personal_slk_internal_ui_messages_render_go", "target": "messages_render_slicecolumns", "relation": "contains", "confidence": "EXTRACTED", "source_file": "internal/ui/messages/render.go", "source_location": "L1148", "weight": 1.0}, {"source": "messages_render_slicecolumns", "target": "messages_plainline", "relation": "references", "confidence": "EXTRACTED", "source_file": "internal/ui/messages/render.go", "source_location": "L1148", "weight": 1.0, "context": "parameter_type"}, {"source": "users_siltala_dev_personal_slk_internal_ui_messages_render_go", "target": "messages_render_plainlines", "relation": "contains", "confidence": "EXTRACTED", "source_file": "internal/ui/messages/render.go", "source_location": "L1168", "weight": 1.0}, {"source": "messages_render_plainlines", "target": "messages_plainline", "relation": "references", "confidence": "EXTRACTED", "source_file": "internal/ui/messages/render.go", "source_location": "L1168", "weight": 1.0, "context": "return_type"}, {"source": "users_siltala_dev_personal_slk_internal_ui_messages_render_go", "target": "messages_render_displaywidthofplain", "relation": "contains", "confidence": "EXTRACTED", "source_file": "internal/ui/messages/render.go", "source_location": "L1171", "weight": 1.0}, {"source": "messages_render_displaywidthofplain", "target": "messages_plainline", "relation": "references", "confidence": "EXTRACTED", "source_file": "internal/ui/messages/render.go", "source_location": "L1171", "weight": 1.0, "context": "parameter_type"}, {"source": "users_siltala_dev_personal_slk_internal_ui_messages_render_go", "target": "messages_render_slicecolumns", "relation": "contains", "confidence": "EXTRACTED", "source_file": "internal/ui/messages/render.go", "source_location": "L1174", "weight": 1.0}, {"source": "messages_render_slicecolumns", "target": "messages_plainline", "relation": "references", "confidence": "EXTRACTED", "source_file": "internal/ui/messages/render.go", "source_location": "L1174", "weight": 1.0, "context": "parameter_type"}, {"source": "messages_render_renderattachments", "target": "messages_render_rendersingleattachment", "relation": "calls", "context": "call", "confidence": "EXTRACTED", "source_file": "internal/ui/messages/render.go", "source_location": "L147", "weight": 1.0}, {"source": "messages_render_rendersingleattachment", "target": "messages_render_linkstyle", "relation": "calls", "context": "call", "confidence": "EXTRACTED", "source_file": "internal/ui/messages/render.go", "source_location": "L159", "weight": 1.0}, {"source": "messages_render_rendersingleattachment", "target": "messages_render_osc8hyperlink", "relation": "calls", "context": "call", "confidence": "EXTRACTED", "source_file": "internal/ui/messages/render.go", "source_location": "L165", "weight": 1.0}, {"source": "messages_render_wordwrap", "target": "messages_render_wrapline", "relation": "calls", "context": "call", "confidence": "EXTRACTED", "source_file": "internal/ui/messages/render.go", "source_location": "L198", "weight": 1.0}, {"source": "messages_render_selectiontintbgansi", "target": "messages_render_bgansifor", "relation": "calls", "context": "call", "confidence": "EXTRACTED", "source_file": "internal/ui/messages/render.go", "source_location": "L305", "weight": 1.0}, {"source": "messages_render_repaintbgtoselectiontint", "target": "messages_render_bgsgrparams", "relation": "calls", "context": "call", "confidence": "EXTRACTED", "source_file": "internal/ui/messages/render.go", "source_location": "L340", "weight": 1.0}, {"source": "messages_render_repaintbgtoselectiontint", "target": "messages_render_bgansi", "relation": "calls", "context": "call", "confidence": "EXTRACTED", "source_file": "internal/ui/messages/render.go", "source_location": "L340", "weight": 1.0}, {"source": "messages_render_repaintbgtoselectiontint", "target": "messages_render_selectiontintbgansi", "relation": "calls", "context": "call", "confidence": "EXTRACTED", "source_file": "internal/ui/messages/render.go", "source_location": "L341", "weight": 1.0}, {"source": "messages_render_repaintbgtoselectiontint", "target": "messages_render_substitutebgsgr", "relation": "calls", "context": "call", "confidence": "EXTRACTED", "source_file": "internal/ui/messages/render.go", "source_location": "L345", "weight": 1.0}, {"source": "messages_render_substitutebgsgr", "target": "messages_render_splitsgrparams", "relation": "calls", "context": "call", "confidence": "EXTRACTED", "source_file": "internal/ui/messages/render.go", "source_location": "L407", "weight": 1.0}, {"source": "messages_render_splitsgrparams", "target": "messages_render_isbasicbgparam", "relation": "calls", "context": "call", "confidence": "EXTRACTED", "source_file": "internal/ui/messages/render.go", "source_location": "L477", "weight": 1.0}, {"source": "messages_render_bgansi", "target": "messages_render_bgansifor", "relation": "calls", "context": "call", "confidence": "EXTRACTED", "source_file": "internal/ui/messages/render.go", "source_location": "L543", "weight": 1.0}, {"source": "messages_render_sidebarbgansi", "target": "messages_render_bgansifor", "relation": "calls", "context": "call", "confidence": "EXTRACTED", "source_file": "internal/ui/messages/render.go", "source_location": "L559", "weight": 1.0}, {"source": "messages_render_fgansi", "target": "messages_render_fgansifor", "relation": "calls", "context": "call", "confidence": "EXTRACTED", "source_file": "internal/ui/messages/render.go", "source_location": "L574", "weight": 1.0}, {"source": "messages_render_sidebarfgansi", "target": "messages_render_fgansifor", "relation": "calls", "context": "call", "confidence": "EXTRACTED", "source_file": "internal/ui/messages/render.go", "source_location": "L585", "weight": 1.0}, {"source": "messages_render_sidebarmutedfgansi", "target": "messages_render_fgansifor", "relation": "calls", "context": "call", "confidence": "EXTRACTED", "source_file": "internal/ui/messages/render.go", "source_location": "L603", "weight": 1.0}, {"source": "messages_render_renderslackmarkdown", "target": "messages_render_renderslackmarkdownwith", "relation": "calls", "context": "call", "confidence": "EXTRACTED", "source_file": "internal/ui/messages/render.go", "source_location": "L642", "weight": 1.0}, {"source": "messages_render_renderslackmarkdownwith", "target": "messages_render_codeblockstyle", "relation": "calls", "context": "call", "confidence": "EXTRACTED", "source_file": "internal/ui/messages/render.go", "source_location": "L656", "weight": 1.0}, {"source": "messages_render_renderslackmarkdownwith", "target": "messages_render_blockquotestyle", "relation": "calls", "context": "call", "confidence": "EXTRACTED", "source_file": "internal/ui/messages/render.go", "source_location": "L667", "weight": 1.0}, {"source": "messages_render_renderslackmarkdownwith", "target": "messages_render_renderinlineformattingwith", "relation": "calls", "context": "call", "confidence": "EXTRACTED", "source_file": "internal/ui/messages/render.go", "source_location": "L669", "weight": 1.0}, {"source": "messages_render_renderslackmarkdownwith", "target": "messages_render_reapplybgafterresets", "relation": "calls", "context": "call", "confidence": "EXTRACTED", "source_file": "internal/ui/messages/render.go", "source_location": "L686", "weight": 1.0}, {"source": "messages_render_renderslackmarkdownwith", "target": "messages_render_bgansi", "relation": "calls", "context": "call", "confidence": "EXTRACTED", "source_file": "internal/ui/messages/render.go", "source_location": "L686", "weight": 1.0}, {"source": "messages_render_renderslackmarkdownwith", "target": "messages_render_fgansi", "relation": "calls", "context": "call", "confidence": "EXTRACTED", "source_file": "internal/ui/messages/render.go", "source_location": "L686", "weight": 1.0}, {"source": "messages_render_renderinlineformattingwith", "target": "messages_render_codestyle", "relation": "calls", "context": "call", "confidence": "EXTRACTED", "source_file": "internal/ui/messages/render.go", "source_location": "L698", "weight": 1.0}, {"source": "messages_render_renderinlineformattingwith", "target": "messages_render_boldstyle", "relation": "calls", "context": "call", "confidence": "EXTRACTED", "source_file": "internal/ui/messages/render.go", "source_location": "L704", "weight": 1.0}, {"source": "messages_render_renderinlineformattingwith", "target": "messages_render_renderitalics", "relation": "calls", "context": "call", "confidence": "EXTRACTED", "source_file": "internal/ui/messages/render.go", "source_location": "L713", "weight": 1.0}, {"source": "messages_render_renderinlineformattingwith", "target": "messages_render_strikethroughstyle", "relation": "calls", "context": "call", "confidence": "EXTRACTED", "source_file": "internal/ui/messages/render.go", "source_location": "L718", "weight": 1.0}, {"source": "messages_render_renderinlineformattingwith", "target": "messages_render_osc8hyperlink", "relation": "calls", "context": "call", "confidence": "EXTRACTED", "source_file": "internal/ui/messages/render.go", "source_location": "L729", "weight": 1.0}, {"source": "messages_render_renderinlineformattingwith", "target": "messages_render_linkstyle", "relation": "calls", "context": "call", "confidence": "EXTRACTED", "source_file": "internal/ui/messages/render.go", "source_location": "L729", "weight": 1.0}, {"source": "messages_render_renderinlineformattingwith", "target": "messages_render_mentionstyle", "relation": "calls", "context": "call", "confidence": "EXTRACTED", "source_file": "internal/ui/messages/render.go", "source_location": "L761", "weight": 1.0}, {"source": "messages_render_renderinlineformattingwith", "target": "messages_render_renderemojitokensinline", "relation": "calls", "context": "call", "confidence": "EXTRACTED", "source_file": "internal/ui/messages/render.go", "source_location": "L819", "weight": 1.0}, {"source": "messages_render_slackmrkdwntocommonmark", "target": "messages_render_slackmrkdwntocommonmarkinline", "relation": "calls", "context": "call", "confidence": "EXTRACTED", "source_file": "internal/ui/messages/render.go", "source_location": "L905", "weight": 1.0}, {"source": "messages_render_slackmrkdwntocommonmarkinline", "target": "messages_render_resolveshortcodescommonmark", "relation": "calls", "context": "call", "confidence": "EXTRACTED", "source_file": "internal/ui/messages/render.go", "source_location": "L972", "weight": 1.0}, {"source": "messages_render_renderitalics", "target": "messages_render_isitalicwordrune", "relation": "calls", "context": "call", "confidence": "EXTRACTED", "source_file": "internal/ui/messages/render.go", "source_location": "L1015", "weight": 1.0}, {"source": "messages_render_renderitalics", "target": "messages_render_italicstyle", "relation": "calls", "context": "call", "confidence": "EXTRACTED", "source_file": "internal/ui/messages/render.go", "source_location": "L1039", "weight": 1.0}, {"source": "messages_render_plainlines", "target": "messages_render_buildplainline", "relation": "calls", "context": "call", "confidence": "EXTRACTED", "source_file": "internal/ui/messages/render.go", "source_location": "L1095", "weight": 1.0}, {"source": "messages_render_slicecolumns", "target": "messages_render_displaywidthofplain", "relation": "calls", "context": "call", "confidence": "EXTRACTED", "source_file": "internal/ui/messages/render.go", "source_location": "L1149", "weight": 1.0}], "raw_calls": [{"caller_nid": "messages_render_boldstyle", "callee": "Foreground", "is_member_call": true, "source_file": "/Users/siltala/dev/personal/slk/internal/ui/messages/render.go", "source_location": "L87"}, {"caller_nid": "messages_render_boldstyle", "callee": "Bold", "is_member_call": true, "source_file": "/Users/siltala/dev/personal/slk/internal/ui/messages/render.go", "source_location": "L87"}, {"caller_nid": "messages_render_boldstyle", "callee": "NewStyle", "is_member_call": true, "source_file": "/Users/siltala/dev/personal/slk/internal/ui/messages/render.go", "source_location": "L87"}, {"caller_nid": "messages_render_italicstyle", "callee": "Foreground", "is_member_call": true, "source_file": "/Users/siltala/dev/personal/slk/internal/ui/messages/render.go", "source_location": "L90"}, {"caller_nid": "messages_render_italicstyle", "callee": "Italic", "is_member_call": true, "source_file": "/Users/siltala/dev/personal/slk/internal/ui/messages/render.go", "source_location": "L90"}, {"caller_nid": "messages_render_italicstyle", "callee": "NewStyle", "is_member_call": true, "source_file": "/Users/siltala/dev/personal/slk/internal/ui/messages/render.go", "source_location": "L90"}, {"caller_nid": "messages_render_strikethroughstyle", "callee": "Foreground", "is_member_call": true, "source_file": "/Users/siltala/dev/personal/slk/internal/ui/messages/render.go", "source_location": "L93"}, {"caller_nid": "messages_render_strikethroughstyle", "callee": "Strikethrough", "is_member_call": true, "source_file": "/Users/siltala/dev/personal/slk/internal/ui/messages/render.go", "source_location": "L93"}, {"caller_nid": "messages_render_strikethroughstyle", "callee": "NewStyle", "is_member_call": true, "source_file": "/Users/siltala/dev/personal/slk/internal/ui/messages/render.go", "source_location": "L93"}, {"caller_nid": "messages_render_codestyle", "callee": "Background", "is_member_call": true, "source_file": "/Users/siltala/dev/personal/slk/internal/ui/messages/render.go", "source_location": "L96"}, {"caller_nid": "messages_render_codestyle", "callee": "Foreground", "is_member_call": true, "source_file": "/Users/siltala/dev/personal/slk/internal/ui/messages/render.go", "source_location": "L96"}, {"caller_nid": "messages_render_codestyle", "callee": "NewStyle", "is_member_call": true, "source_file": "/Users/siltala/dev/personal/slk/internal/ui/messages/render.go", "source_location": "L96"}, {"caller_nid": "messages_render_codeblockstyle", "callee": "Padding", "is_member_call": true, "source_file": "/Users/siltala/dev/personal/slk/internal/ui/messages/render.go", "source_location": "L101"}, {"caller_nid": "messages_render_codeblockstyle", "callee": "Background", "is_member_call": true, "source_file": "/Users/siltala/dev/personal/slk/internal/ui/messages/render.go", "source_location": "L101"}, {"caller_nid": "messages_render_codeblockstyle", "callee": "Foreground", "is_member_call": true, "source_file": "/Users/siltala/dev/personal/slk/internal/ui/messages/render.go", "source_location": "L101"}, {"caller_nid": "messages_render_codeblockstyle", "callee": "NewStyle", "is_member_call": true, "source_file": "/Users/siltala/dev/personal/slk/internal/ui/messages/render.go", "source_location": "L101"}, {"caller_nid": "messages_render_linkstyle", "callee": "Underline", "is_member_call": true, "source_file": "/Users/siltala/dev/personal/slk/internal/ui/messages/render.go", "source_location": "L107"}, {"caller_nid": "messages_render_linkstyle", "callee": "Foreground", "is_member_call": true, "source_file": "/Users/siltala/dev/personal/slk/internal/ui/messages/render.go", "source_location": "L107"}, {"caller_nid": "messages_render_linkstyle", "callee": "NewStyle", "is_member_call": true, "source_file": "/Users/siltala/dev/personal/slk/internal/ui/messages/render.go", "source_location": "L107"}, {"caller_nid": "messages_render_mentionstyle", "callee": "Bold", "is_member_call": true, "source_file": "/Users/siltala/dev/personal/slk/internal/ui/messages/render.go", "source_location": "L112"}, {"caller_nid": "messages_render_mentionstyle", "callee": "Foreground", "is_member_call": true, "source_file": "/Users/siltala/dev/personal/slk/internal/ui/messages/render.go", "source_location": "L112"}, {"caller_nid": "messages_render_mentionstyle", "callee": "NewStyle", "is_member_call": true, "source_file": "/Users/siltala/dev/personal/slk/internal/ui/messages/render.go", "source_location": "L112"}, {"caller_nid": "messages_render_blockquotestyle", "callee": "PaddingLeft", "is_member_call": true, "source_file": "/Users/siltala/dev/personal/slk/internal/ui/messages/render.go", "source_location": "L117"}, {"caller_nid": "messages_render_blockquotestyle", "callee": "BorderForeground", "is_member_call": true, "source_file": "/Users/siltala/dev/personal/slk/internal/ui/messages/render.go", "source_location": "L117"}, {"caller_nid": "messages_render_blockquotestyle", "callee": "BorderLeft", "is_member_call": true, "source_file": "/Users/siltala/dev/personal/slk/internal/ui/messages/render.go", "source_location": "L117"}, {"caller_nid": "messages_render_blockquotestyle", "callee": "BorderStyle", "is_member_call": true, "source_file": "/Users/siltala/dev/personal/slk/internal/ui/messages/render.go", "source_location": "L117"}, {"caller_nid": "messages_render_blockquotestyle", "callee": "Foreground", "is_member_call": true, "source_file": "/Users/siltala/dev/personal/slk/internal/ui/messages/render.go", "source_location": "L117"}, {"caller_nid": "messages_render_blockquotestyle", "callee": "NewStyle", "is_member_call": true, "source_file": "/Users/siltala/dev/personal/slk/internal/ui/messages/render.go", "source_location": "L117"}, {"caller_nid": "messages_render_blockquotestyle", "callee": "ThickBorder", "is_member_call": true, "source_file": "/Users/siltala/dev/personal/slk/internal/ui/messages/render.go", "source_location": "L119"}, {"caller_nid": "messages_render_renderattachments", "callee": "make", "is_member_call": false, "source_file": "/Users/siltala/dev/personal/slk/internal/ui/messages/render.go", "source_location": "L145"}, {"caller_nid": "messages_render_renderattachments", "callee": "append", "is_member_call": false, "source_file": "/Users/siltala/dev/personal/slk/internal/ui/messages/render.go", "source_location": "L147"}, {"caller_nid": "messages_render_renderattachments", "callee": "Join", "is_member_call": false, "source_file": "/Users/siltala/dev/personal/slk/internal/ui/messages/render.go", "source_location": "L149"}, {"caller_nid": "messages_render_rendersingleattachment", "callee": "Bold", "is_member_call": true, "source_file": "/Users/siltala/dev/personal/slk/internal/ui/messages/render.go", "source_location": "L158"}, {"caller_nid": "messages_render_rendersingleattachment", "callee": "Foreground", "is_member_call": true, "source_file": "/Users/siltala/dev/personal/slk/internal/ui/messages/render.go", "source_location": "L158"}, {"caller_nid": "messages_render_rendersingleattachment", "callee": "NewStyle", "is_member_call": true, "source_file": "/Users/siltala/dev/personal/slk/internal/ui/messages/render.go", "source_location": "L158"}, {"caller_nid": "messages_render_rendersingleattachment", "callee": "Render", "is_member_call": true, "source_file": "/Users/siltala/dev/personal/slk/internal/ui/messages/render.go", "source_location": "L164"}, {"caller_nid": "messages_render_rendersingleattachment", "callee": "Render", "is_member_call": true, "source_file": "/Users/siltala/dev/personal/slk/internal/ui/messages/render.go", "source_location": "L164"}, {"caller_nid": "messages_render_wordwrap", "callee": "Split", "is_member_call": false, "source_file": "/Users/siltala/dev/personal/slk/internal/ui/messages/render.go", "source_location": "L194"}, {"caller_nid": "messages_render_wordwrap", "callee": "WriteByte", "is_member_call": true, "source_file": "/Users/siltala/dev/personal/slk/internal/ui/messages/render.go", "source_location": "L196"}, {"caller_nid": "messages_render_wrapline", "callee": "Fields", "is_member_call": false, "source_file": "/Users/siltala/dev/personal/slk/internal/ui/messages/render.go", "source_location": "L210"}, {"caller_nid": "messages_render_wrapline", "callee": "Width", "is_member_call": true, "source_file": "/Users/siltala/dev/personal/slk/internal/ui/messages/render.go", "source_location": "L219"}, {"caller_nid": "messages_render_wrapline", "callee": "WriteString", "is_member_call": true, "source_file": "/Users/siltala/dev/personal/slk/internal/ui/messages/render.go", "source_location": "L221"}, {"caller_nid": "messages_render_wrapline", "callee": "Hardwrap", "is_member_call": false, "source_file": "/Users/siltala/dev/personal/slk/internal/ui/messages/render.go", "source_location": "L225"}, {"caller_nid": "messages_render_wrapline", "callee": "WriteString", "is_member_call": true, "source_file": "/Users/siltala/dev/personal/slk/internal/ui/messages/render.go", "source_location": "L226"}, {"caller_nid": "messages_render_wrapline", "callee": "LastIndexByte", "is_member_call": false, "source_file": "/Users/siltala/dev/personal/slk/internal/ui/messages/render.go", "source_location": "L229"}, {"caller_nid": "messages_render_wrapline", "callee": "Width", "is_member_call": true, "source_file": "/Users/siltala/dev/personal/slk/internal/ui/messages/render.go", "source_location": "L230"}, {"caller_nid": "messages_render_wrapline", "callee": "Width", "is_member_call": true, "source_file": "/Users/siltala/dev/personal/slk/internal/ui/messages/render.go", "source_location": "L232"}, {"caller_nid": "messages_render_wrapline", "callee": "Width", "is_member_call": true, "source_file": "/Users/siltala/dev/personal/slk/internal/ui/messages/render.go", "source_location": "L237"}, {"caller_nid": "messages_render_wrapline", "callee": "writeWord", "is_member_call": false, "source_file": "/Users/siltala/dev/personal/slk/internal/ui/messages/render.go", "source_location": "L239"}, {"caller_nid": "messages_render_wrapline", "callee": "WriteByte", "is_member_call": true, "source_file": "/Users/siltala/dev/personal/slk/internal/ui/messages/render.go", "source_location": "L244"}, {"caller_nid": "messages_render_wrapline", "callee": "writeWord", "is_member_call": false, "source_file": "/Users/siltala/dev/personal/slk/internal/ui/messages/render.go", "source_location": "L245"}, {"caller_nid": "messages_render_wrapline", "callee": "WriteByte", "is_member_call": true, "source_file": "/Users/siltala/dev/personal/slk/internal/ui/messages/render.go", "source_location": "L247"}, {"caller_nid": "messages_render_wrapline", "callee": "WriteString", "is_member_call": true, "source_file": "/Users/siltala/dev/personal/slk/internal/ui/messages/render.go", "source_location": "L248"}, {"caller_nid": "messages_render_reapplybgafterresets", "callee": "ReplaceAll", "is_member_call": false, "source_file": "/Users/siltala/dev/personal/slk/internal/ui/messages/render.go", "source_location": "L269"}, {"caller_nid": "messages_render_selectiontintbgansi", "callee": "SelectionTintColor", "is_member_call": false, "source_file": "/Users/siltala/dev/personal/slk/internal/ui/messages/render.go", "source_location": "L300"}, {"caller_nid": "messages_render_bgsgrparams", "callee": "HasPrefix", "is_member_call": false, "source_file": "/Users/siltala/dev/personal/slk/internal/ui/messages/render.go", "source_location": "L354"}, {"caller_nid": "messages_render_bgsgrparams", "callee": "HasSuffix", "is_member_call": false, "source_file": "/Users/siltala/dev/personal/slk/internal/ui/messages/render.go", "source_location": "L354"}, {"caller_nid": "messages_render_substitutebgsgr", "callee": "Grow", "is_member_call": true, "source_file": "/Users/siltala/dev/personal/slk/internal/ui/messages/render.go", "source_location": "L378"}, {"caller_nid": "messages_render_substitutebgsgr", "callee": "Index", "is_member_call": false, "source_file": "/Users/siltala/dev/personal/slk/internal/ui/messages/render.go", "source_location": "L381"}, {"caller_nid": "messages_render_substitutebgsgr", "callee": "WriteString", "is_member_call": true, "source_file": "/Users/siltala/dev/personal/slk/internal/ui/messages/render.go", "source_location": "L383"}, {"caller_nid": "messages_render_substitutebgsgr", "callee": "WriteString", "is_member_call": true, "source_file": "/Users/siltala/dev/personal/slk/internal/ui/messages/render.go", "source_location": "L387"}, {"caller_nid": "messages_render_substitutebgsgr", "callee": "WriteString", "is_member_call": true, "source_file": "/Users/siltala/dev/personal/slk/internal/ui/messages/render.go", "source_location": "L402"}, {"caller_nid": "messages_render_substitutebgsgr", "callee": "make", "is_member_call": false, "source_file": "/Users/siltala/dev/personal/slk/internal/ui/messages/render.go", "source_location": "L408"}, {"caller_nid": "messages_render_substitutebgsgr", "callee": "append", "is_member_call": false, "source_file": "/Users/siltala/dev/personal/slk/internal/ui/messages/render.go", "source_location": "L411"}, {"caller_nid": "messages_render_substitutebgsgr", "callee": "append", "is_member_call": false, "source_file": "/Users/siltala/dev/personal/slk/internal/ui/messages/render.go", "source_location": "L413"}, {"caller_nid": "messages_render_substitutebgsgr", "callee": "WriteString", "is_member_call": true, "source_file": "/Users/siltala/dev/personal/slk/internal/ui/messages/render.go", "source_location": "L416"}, {"caller_nid": "messages_render_substitutebgsgr", "callee": "WriteString", "is_member_call": true, "source_file": "/Users/siltala/dev/personal/slk/internal/ui/messages/render.go", "source_location": "L417"}, {"caller_nid": "messages_render_substitutebgsgr", "callee": "Join", "is_member_call": false, "source_file": "/Users/siltala/dev/personal/slk/internal/ui/messages/render.go", "source_location": "L417"}, {"caller_nid": "messages_render_substitutebgsgr", "callee": "WriteString", "is_member_call": true, "source_file": "/Users/siltala/dev/personal/slk/internal/ui/messages/render.go", "source_location": "L418"}, {"caller_nid": "messages_render_splitsgrparams", "callee": "Split", "is_member_call": false, "source_file": "/Users/siltala/dev/personal/slk/internal/ui/messages/render.go", "source_location": "L442"}, {"caller_nid": "messages_render_splitsgrparams", "callee": "make", "is_member_call": false, "source_file": "/Users/siltala/dev/personal/slk/internal/ui/messages/render.go", "source_location": "L443"}, {"caller_nid": "messages_render_splitsgrparams", "callee": "append", "is_member_call": false, "source_file": "/Users/siltala/dev/personal/slk/internal/ui/messages/render.go", "source_location": "L454"}, {"caller_nid": "messages_render_splitsgrparams", "callee": "Join", "is_member_call": false, "source_file": "/Users/siltala/dev/personal/slk/internal/ui/messages/render.go", "source_location": "L455"}, {"caller_nid": "messages_render_splitsgrparams", "callee": "append", "is_member_call": false, "source_file": "/Users/siltala/dev/personal/slk/internal/ui/messages/render.go", "source_location": "L463"}, {"caller_nid": "messages_render_splitsgrparams", "callee": "Join", "is_member_call": false, "source_file": "/Users/siltala/dev/personal/slk/internal/ui/messages/render.go", "source_location": "L464"}, {"caller_nid": "messages_render_splitsgrparams", "callee": "append", "is_member_call": false, "source_file": "/Users/siltala/dev/personal/slk/internal/ui/messages/render.go", "source_location": "L473"}, {"caller_nid": "messages_render_splitsgrparams", "callee": "append", "is_member_call": false, "source_file": "/Users/siltala/dev/personal/slk/internal/ui/messages/render.go", "source_location": "L475"}, {"caller_nid": "messages_render_bgansifor", "callee": "Sprintf", "is_member_call": false, "source_file": "/Users/siltala/dev/personal/slk/internal/ui/messages/render.go", "source_location": "L504"}, {"caller_nid": "messages_render_bgansifor", "callee": "Sprintf", "is_member_call": false, "source_file": "/Users/siltala/dev/personal/slk/internal/ui/messages/render.go", "source_location": "L507"}, {"caller_nid": "messages_render_bgansifor", "callee": "Sprintf", "is_member_call": false, "source_file": "/Users/siltala/dev/personal/slk/internal/ui/messages/render.go", "source_location": "L511"}, {"caller_nid": "messages_render_bgansifor", "callee": "RGBA", "is_member_call": true, "source_file": "/Users/siltala/dev/personal/slk/internal/ui/messages/render.go", "source_location": "L513"}, {"caller_nid": "messages_render_bgansifor", "callee": "Sprintf", "is_member_call": false, "source_file": "/Users/siltala/dev/personal/slk/internal/ui/messages/render.go", "source_location": "L514"}, {"caller_nid": "messages_render_fgansifor", "callee": "Sprintf", "is_member_call": false, "source_file": "/Users/siltala/dev/personal/slk/internal/ui/messages/render.go", "source_location": "L523"}, {"caller_nid": "messages_render_fgansifor", "callee": "Sprintf", "is_member_call": false, "source_file": "/Users/siltala/dev/personal/slk/internal/ui/messages/render.go", "source_location": "L526"}, {"caller_nid": "messages_render_fgansifor", "callee": "Sprintf", "is_member_call": false, "source_file": "/Users/siltala/dev/personal/slk/internal/ui/messages/render.go", "source_location": "L529"}, {"caller_nid": "messages_render_fgansifor", "callee": "RGBA", "is_member_call": true, "source_file": "/Users/siltala/dev/personal/slk/internal/ui/messages/render.go", "source_location": "L531"}, {"caller_nid": "messages_render_fgansifor", "callee": "Sprintf", "is_member_call": false, "source_file": "/Users/siltala/dev/personal/slk/internal/ui/messages/render.go", "source_location": "L532"}, {"caller_nid": "messages_render_renderslackmarkdownwith", "callee": "ReplaceAllStringFunc", "is_member_call": true, "source_file": "/Users/siltala/dev/personal/slk/internal/ui/messages/render.go", "source_location": "L653"}, {"caller_nid": "messages_render_renderslackmarkdownwith", "callee": "FindStringSubmatch", "is_member_call": true, "source_file": "/Users/siltala/dev/personal/slk/internal/ui/messages/render.go", "source_location": "L654"}, {"caller_nid": "messages_render_renderslackmarkdownwith", "callee": "TrimSpace", "is_member_call": false, "source_file": "/Users/siltala/dev/personal/slk/internal/ui/messages/render.go", "source_location": "L655"}, {"caller_nid": "messages_render_renderslackmarkdownwith", "callee": "Render", "is_member_call": true, "source_file": "/Users/siltala/dev/personal/slk/internal/ui/messages/render.go", "source_location": "L656"}, {"caller_nid": "messages_render_renderslackmarkdownwith", "callee": "Split", "is_member_call": false, "source_file": "/Users/siltala/dev/personal/slk/internal/ui/messages/render.go", "source_location": "L660"}, {"caller_nid": "messages_render_renderslackmarkdownwith", "callee": "HasPrefix", "is_member_call": false, "source_file": "/Users/siltala/dev/personal/slk/internal/ui/messages/render.go", "source_location": "L663"}, {"caller_nid": "messages_render_renderslackmarkdownwith", "callee": "HasPrefix", "is_member_call": false, "source_file": "/Users/siltala/dev/personal/slk/internal/ui/messages/render.go", "source_location": "L663"}, {"caller_nid": "messages_render_renderslackmarkdownwith", "callee": "TrimPrefix", "is_member_call": false, "source_file": "/Users/siltala/dev/personal/slk/internal/ui/messages/render.go", "source_location": "L664"}, {"caller_nid": "messages_render_renderslackmarkdownwith", "callee": "TrimPrefix", "is_member_call": false, "source_file": "/Users/siltala/dev/personal/slk/internal/ui/messages/render.go", "source_location": "L665"}, {"caller_nid": "messages_render_renderslackmarkdownwith", "callee": "Replace", "is_member_call": true, "source_file": "/Users/siltala/dev/personal/slk/internal/ui/messages/render.go", "source_location": "L666"}, {"caller_nid": "messages_render_renderslackmarkdownwith", "callee": "Render", "is_member_call": true, "source_file": "/Users/siltala/dev/personal/slk/internal/ui/messages/render.go", "source_location": "L667"}, {"caller_nid": "messages_render_renderslackmarkdownwith", "callee": "Replace", "is_member_call": true, "source_file": "/Users/siltala/dev/personal/slk/internal/ui/messages/render.go", "source_location": "L673"}, {"caller_nid": "messages_render_renderslackmarkdownwith", "callee": "append", "is_member_call": false, "source_file": "/Users/siltala/dev/personal/slk/internal/ui/messages/render.go", "source_location": "L675"}, {"caller_nid": "messages_render_renderslackmarkdownwith", "callee": "Join", "is_member_call": false, "source_file": "/Users/siltala/dev/personal/slk/internal/ui/messages/render.go", "source_location": "L678"}, {"caller_nid": "messages_render_renderinlineformattingwith", "callee": "ReplaceAllStringFunc", "is_member_call": true, "source_file": "/Users/siltala/dev/personal/slk/internal/ui/messages/render.go", "source_location": "L696"}, {"caller_nid": "messages_render_renderinlineformattingwith", "callee": "FindStringSubmatch", "is_member_call": true, "source_file": "/Users/siltala/dev/personal/slk/internal/ui/messages/render.go", "source_location": "L697"}, {"caller_nid": "messages_render_renderinlineformattingwith", "callee": "Render", "is_member_call": true, "source_file": "/Users/siltala/dev/personal/slk/internal/ui/messages/render.go", "source_location": "L698"}, {"caller_nid": "messages_render_renderinlineformattingwith", "callee": "ReplaceAllStringFunc", "is_member_call": true, "source_file": "/Users/siltala/dev/personal/slk/internal/ui/messages/render.go", "source_location": "L702"}, {"caller_nid": "messages_render_renderinlineformattingwith", "callee": "FindStringSubmatch", "is_member_call": true, "source_file": "/Users/siltala/dev/personal/slk/internal/ui/messages/render.go", "source_location": "L703"}, {"caller_nid": "messages_render_renderinlineformattingwith", "callee": "Render", "is_member_call": true, "source_file": "/Users/siltala/dev/personal/slk/internal/ui/messages/render.go", "source_location": "L704"}, {"caller_nid": "messages_render_renderinlineformattingwith", "callee": "ReplaceAllStringFunc", "is_member_call": true, "source_file": "/Users/siltala/dev/personal/slk/internal/ui/messages/render.go", "source_location": "L716"}, {"caller_nid": "messages_render_renderinlineformattingwith", "callee": "FindStringSubmatch", "is_member_call": true, "source_file": "/Users/siltala/dev/personal/slk/internal/ui/messages/render.go", "source_location": "L717"}, {"caller_nid": "messages_render_renderinlineformattingwith", "callee": "Render", "is_member_call": true, "source_file": "/Users/siltala/dev/personal/slk/internal/ui/messages/render.go", "source_location": "L718"}, {"caller_nid": "messages_render_renderinlineformattingwith", "callee": "ReplaceAllStringFunc", "is_member_call": true, "source_file": "/Users/siltala/dev/personal/slk/internal/ui/messages/render.go", "source_location": "L726"}, {"caller_nid": "messages_render_renderinlineformattingwith", "callee": "FindStringSubmatch", "is_member_call": true, "source_file": "/Users/siltala/dev/personal/slk/internal/ui/messages/render.go", "source_location": "L727"}, {"caller_nid": "messages_render_renderinlineformattingwith", "callee": "Render", "is_member_call": true, "source_file": "/Users/siltala/dev/personal/slk/internal/ui/messages/render.go", "source_location": "L729"}, {"caller_nid": "messages_render_renderinlineformattingwith", "callee": "ReplaceAllStringFunc", "is_member_call": true, "source_file": "/Users/siltala/dev/personal/slk/internal/ui/messages/render.go", "source_location": "L736"}, {"caller_nid": "messages_render_renderinlineformattingwith", "callee": "FindStringSubmatch", "is_member_call": true, "source_file": "/Users/siltala/dev/personal/slk/internal/ui/messages/render.go", "source_location": "L737"}, {"caller_nid": "messages_render_renderinlineformattingwith", "callee": "TrimPrefix", "is_member_call": false, "source_file": "/Users/siltala/dev/personal/slk/internal/ui/messages/render.go", "source_location": "L738"}, {"caller_nid": "messages_render_renderinlineformattingwith", "callee": "Render", "is_member_call": true, "source_file": "/Users/siltala/dev/personal/slk/internal/ui/messages/render.go", "source_location": "L739"}, {"caller_nid": "messages_render_renderinlineformattingwith", "callee": "ReplaceAllStringFunc", "is_member_call": true, "source_file": "/Users/siltala/dev/personal/slk/internal/ui/messages/render.go", "source_location": "L746"}, {"caller_nid": "messages_render_renderinlineformattingwith", "callee": "FindStringSubmatch", "is_member_call": true, "source_file": "/Users/siltala/dev/personal/slk/internal/ui/messages/render.go", "source_location": "L747"}, {"caller_nid": "messages_render_renderinlineformattingwith", "callee": "Render", "is_member_call": true, "source_file": "/Users/siltala/dev/personal/slk/internal/ui/messages/render.go", "source_location": "L761"}, {"caller_nid": "messages_render_renderinlineformattingwith", "callee": "ReplaceAllStringFunc", "is_member_call": true, "source_file": "/Users/siltala/dev/personal/slk/internal/ui/messages/render.go", "source_location": "L768"}, {"caller_nid": "messages_render_renderinlineformattingwith", "callee": "FindStringSubmatch", "is_member_call": true, "source_file": "/Users/siltala/dev/personal/slk/internal/ui/messages/render.go", "source_location": "L769"}, {"caller_nid": "messages_render_renderinlineformattingwith", "callee": "Render", "is_member_call": true, "source_file": "/Users/siltala/dev/personal/slk/internal/ui/messages/render.go", "source_location": "L783"}, {"caller_nid": "messages_render_renderinlineformattingwith", "callee": "ReplaceAllStringFunc", "is_member_call": true, "source_file": "/Users/siltala/dev/personal/slk/internal/ui/messages/render.go", "source_location": "L787"}, {"caller_nid": "messages_render_renderinlineformattingwith", "callee": "FindStringSubmatch", "is_member_call": true, "source_file": "/Users/siltala/dev/personal/slk/internal/ui/messages/render.go", "source_location": "L788"}, {"caller_nid": "messages_render_renderinlineformattingwith", "callee": "Render", "is_member_call": true, "source_file": "/Users/siltala/dev/personal/slk/internal/ui/messages/render.go", "source_location": "L795"}, {"caller_nid": "messages_render_renderinlineformattingwith", "callee": "ImageModeActive", "is_member_call": false, "source_file": "/Users/siltala/dev/personal/slk/internal/ui/messages/render.go", "source_location": "L817"}, {"caller_nid": "messages_render_renderinlineformattingwith", "callee": "ResolveEmojiToTokens", "is_member_call": false, "source_file": "/Users/siltala/dev/personal/slk/internal/ui/messages/render.go", "source_location": "L818"}, {"caller_nid": "messages_render_renderinlineformattingwith", "callee": "ResolveShortcodesInText", "is_member_call": false, "source_file": "/Users/siltala/dev/personal/slk/internal/ui/messages/render.go", "source_location": "L821"}, {"caller_nid": "messages_render_renderinlineformattingwith", "callee": "StripSkinToneFromText", "is_member_call": false, "source_file": "/Users/siltala/dev/personal/slk/internal/ui/messages/render.go", "source_location": "L821"}, {"caller_nid": "messages_render_renderemojitokensinline", "callee": "ImageModeActive", "is_member_call": false, "source_file": "/Users/siltala/dev/personal/slk/internal/ui/messages/render.go", "source_location": "L846"}, {"caller_nid": "messages_render_renderemojitokensinline", "callee": "WriteString", "is_member_call": true, "source_file": "/Users/siltala/dev/personal/slk/internal/ui/messages/render.go", "source_location": "L852"}, {"caller_nid": "messages_render_renderemojitokensinline", "callee": "Place", "is_member_call": false, "source_file": "/Users/siltala/dev/personal/slk/internal/ui/messages/render.go", "source_location": "L855"}, {"caller_nid": "messages_render_renderemojitokensinline", "callee": "WriteString", "is_member_call": true, "source_file": "/Users/siltala/dev/personal/slk/internal/ui/messages/render.go", "source_location": "L857"}, {"caller_nid": "messages_render_renderemojitokensinline", "callee": "append", "is_member_call": false, "source_file": "/Users/siltala/dev/personal/slk/internal/ui/messages/render.go", "source_location": "L859"}, {"caller_nid": "messages_render_renderemojitokensinline", "callee": "WriteString", "is_member_call": true, "source_file": "/Users/siltala/dev/personal/slk/internal/ui/messages/render.go", "source_location": "L867"}, {"caller_nid": "messages_render_slackmrkdwntocommonmark", "callee": "ReplaceAllStringFunc", "is_member_call": true, "source_file": "/Users/siltala/dev/personal/slk/internal/ui/messages/render.go", "source_location": "L879"}, {"caller_nid": "messages_render_slackmrkdwntocommonmark", "callee": "FindStringSubmatch", "is_member_call": true, "source_file": "/Users/siltala/dev/personal/slk/internal/ui/messages/render.go", "source_location": "L880"}, {"caller_nid": "messages_render_slackmrkdwntocommonmark", "callee": "TrimSpace", "is_member_call": false, "source_file": "/Users/siltala/dev/personal/slk/internal/ui/messages/render.go", "source_location": "L881"}, {"caller_nid": "messages_render_slackmrkdwntocommonmark", "callee": "Sprintf", "is_member_call": false, "source_file": "/Users/siltala/dev/personal/slk/internal/ui/messages/render.go", "source_location": "L882"}, {"caller_nid": "messages_render_slackmrkdwntocommonmark", "callee": "append", "is_member_call": false, "source_file": "/Users/siltala/dev/personal/slk/internal/ui/messages/render.go", "source_location": "L883"}, {"caller_nid": "messages_render_slackmrkdwntocommonmark", "callee": "ReplaceAllStringFunc", "is_member_call": true, "source_file": "/Users/siltala/dev/personal/slk/internal/ui/messages/render.go", "source_location": "L889"}, {"caller_nid": "messages_render_slackmrkdwntocommonmark", "callee": "FindStringSubmatch", "is_member_call": true, "source_file": "/Users/siltala/dev/personal/slk/internal/ui/messages/render.go", "source_location": "L890"}, {"caller_nid": "messages_render_slackmrkdwntocommonmark", "callee": "Sprintf", "is_member_call": false, "source_file": "/Users/siltala/dev/personal/slk/internal/ui/messages/render.go", "source_location": "L891"}, {"caller_nid": "messages_render_slackmrkdwntocommonmark", "callee": "append", "is_member_call": false, "source_file": "/Users/siltala/dev/personal/slk/internal/ui/messages/render.go", "source_location": "L892"}, {"caller_nid": "messages_render_slackmrkdwntocommonmark", "callee": "Split", "is_member_call": false, "source_file": "/Users/siltala/dev/personal/slk/internal/ui/messages/render.go", "source_location": "L896"}, {"caller_nid": "messages_render_slackmrkdwntocommonmark", "callee": "HasPrefix", "is_member_call": false, "source_file": "/Users/siltala/dev/personal/slk/internal/ui/messages/render.go", "source_location": "L899"}, {"caller_nid": "messages_render_slackmrkdwntocommonmark", "callee": "HasPrefix", "is_member_call": false, "source_file": "/Users/siltala/dev/personal/slk/internal/ui/messages/render.go", "source_location": "L899"}, {"caller_nid": "messages_render_slackmrkdwntocommonmark", "callee": "TrimPrefix", "is_member_call": false, "source_file": "/Users/siltala/dev/personal/slk/internal/ui/messages/render.go", "source_location": "L900"}, {"caller_nid": "messages_render_slackmrkdwntocommonmark", "callee": "TrimPrefix", "is_member_call": false, "source_file": "/Users/siltala/dev/personal/slk/internal/ui/messages/render.go", "source_location": "L901"}, {"caller_nid": "messages_render_slackmrkdwntocommonmark", "callee": "Replace", "is_member_call": true, "source_file": "/Users/siltala/dev/personal/slk/internal/ui/messages/render.go", "source_location": "L902"}, {"caller_nid": "messages_render_slackmrkdwntocommonmark", "callee": "Replace", "is_member_call": true, "source_file": "/Users/siltala/dev/personal/slk/internal/ui/messages/render.go", "source_location": "L906"}, {"caller_nid": "messages_render_slackmrkdwntocommonmark", "callee": "append", "is_member_call": false, "source_file": "/Users/siltala/dev/personal/slk/internal/ui/messages/render.go", "source_location": "L908"}, {"caller_nid": "messages_render_slackmrkdwntocommonmark", "callee": "Join", "is_member_call": false, "source_file": "/Users/siltala/dev/personal/slk/internal/ui/messages/render.go", "source_location": "L911"}, {"caller_nid": "messages_render_slackmrkdwntocommonmark", "callee": "Replace", "is_member_call": false, "source_file": "/Users/siltala/dev/personal/slk/internal/ui/messages/render.go", "source_location": "L915"}, {"caller_nid": "messages_render_slackmrkdwntocommonmark", "callee": "Sprintf", "is_member_call": false, "source_file": "/Users/siltala/dev/personal/slk/internal/ui/messages/render.go", "source_location": "L915"}, {"caller_nid": "messages_render_slackmrkdwntocommonmark", "callee": "Replace", "is_member_call": false, "source_file": "/Users/siltala/dev/personal/slk/internal/ui/messages/render.go", "source_location": "L919"}, {"caller_nid": "messages_render_slackmrkdwntocommonmark", "callee": "Sprintf", "is_member_call": false, "source_file": "/Users/siltala/dev/personal/slk/internal/ui/messages/render.go", "source_location": "L919"}, {"caller_nid": "messages_render_slackmrkdwntocommonmarkinline", "callee": "ReplaceAllString", "is_member_call": true, "source_file": "/Users/siltala/dev/personal/slk/internal/ui/messages/render.go", "source_location": "L928"}, {"caller_nid": "messages_render_slackmrkdwntocommonmarkinline", "callee": "ReplaceAllString", "is_member_call": true, "source_file": "/Users/siltala/dev/personal/slk/internal/ui/messages/render.go", "source_location": "L930"}, {"caller_nid": "messages_render_slackmrkdwntocommonmarkinline", "callee": "ReplaceAllStringFunc", "is_member_call": true, "source_file": "/Users/siltala/dev/personal/slk/internal/ui/messages/render.go", "source_location": "L932"}, {"caller_nid": "messages_render_slackmrkdwntocommonmarkinline", "callee": "FindStringSubmatch", "is_member_call": true, "source_file": "/Users/siltala/dev/personal/slk/internal/ui/messages/render.go", "source_location": "L933"}, {"caller_nid": "messages_render_slackmrkdwntocommonmarkinline", "callee": "ReplaceAllStringFunc", "is_member_call": true, "source_file": "/Users/siltala/dev/personal/slk/internal/ui/messages/render.go", "source_location": "L938"}, {"caller_nid": "messages_render_slackmrkdwntocommonmarkinline", "callee": "FindStringSubmatch", "is_member_call": true, "source_file": "/Users/siltala/dev/personal/slk/internal/ui/messages/render.go", "source_location": "L939"}, {"caller_nid": "messages_render_slackmrkdwntocommonmarkinline", "callee": "TrimPrefix", "is_member_call": false, "source_file": "/Users/siltala/dev/personal/slk/internal/ui/messages/render.go", "source_location": "L940"}, {"caller_nid": "messages_render_slackmrkdwntocommonmarkinline", "callee": "ReplaceAllStringFunc", "is_member_call": true, "source_file": "/Users/siltala/dev/personal/slk/internal/ui/messages/render.go", "source_location": "L943"}, {"caller_nid": "messages_render_slackmrkdwntocommonmarkinline", "callee": "FindStringSubmatch", "is_member_call": true, "source_file": "/Users/siltala/dev/personal/slk/internal/ui/messages/render.go", "source_location": "L944"}, {"caller_nid": "messages_render_slackmrkdwntocommonmarkinline", "callee": "ReplaceAllStringFunc", "is_member_call": true, "source_file": "/Users/siltala/dev/personal/slk/internal/ui/messages/render.go", "source_location": "L961"}, {"caller_nid": "messages_render_slackmrkdwntocommonmarkinline", "callee": "FindStringSubmatch", "is_member_call": true, "source_file": "/Users/siltala/dev/personal/slk/internal/ui/messages/render.go", "source_location": "L962"}, {"caller_nid": "messages_render_slackmrkdwntocommonmarkinline", "callee": "StripSkinToneFromText", "is_member_call": false, "source_file": "/Users/siltala/dev/personal/slk/internal/ui/messages/render.go", "source_location": "L972"}, {"caller_nid": "messages_render_resolveshortcodescommonmark", "callee": "ReplaceAllStringFunc", "is_member_call": true, "source_file": "/Users/siltala/dev/personal/slk/internal/ui/messages/render.go", "source_location": "L980"}, {"caller_nid": "messages_render_resolveshortcodescommonmark", "callee": "Sprint", "is_member_call": false, "source_file": "/Users/siltala/dev/personal/slk/internal/ui/messages/render.go", "source_location": "L981"}, {"caller_nid": "messages_render_resolveshortcodescommonmark", "callee": "TrimRight", "is_member_call": false, "source_file": "/Users/siltala/dev/personal/slk/internal/ui/messages/render.go", "source_location": "L985"}, {"caller_nid": "messages_render_renderitalics", "callee": "ContainsRune", "is_member_call": false, "source_file": "/Users/siltala/dev/personal/slk/internal/ui/messages/render.go", "source_location": "L1000"}, {"caller_nid": "messages_render_renderitalics", "callee": "Grow", "is_member_call": true, "source_file": "/Users/siltala/dev/personal/slk/internal/ui/messages/render.go", "source_location": "L1005"}, {"caller_nid": "messages_render_renderitalics", "callee": "WriteRune", "is_member_call": true, "source_file": "/Users/siltala/dev/personal/slk/internal/ui/messages/render.go", "source_location": "L1009"}, {"caller_nid": "messages_render_renderitalics", "callee": "WriteRune", "is_member_call": true, "source_file": "/Users/siltala/dev/personal/slk/internal/ui/messages/render.go", "source_location": "L1016"}, {"caller_nid": "messages_render_renderitalics", "callee": "WriteRune", "is_member_call": true, "source_file": "/Users/siltala/dev/personal/slk/internal/ui/messages/render.go", "source_location": "L1027"}, {"caller_nid": "messages_render_renderitalics", "callee": "WriteRune", "is_member_call": true, "source_file": "/Users/siltala/dev/personal/slk/internal/ui/messages/render.go", "source_location": "L1034"}, {"caller_nid": "messages_render_renderitalics", "callee": "string", "is_member_call": false, "source_file": "/Users/siltala/dev/personal/slk/internal/ui/messages/render.go", "source_location": "L1038"}, {"caller_nid": "messages_render_renderitalics", "callee": "WriteString", "is_member_call": true, "source_file": "/Users/siltala/dev/personal/slk/internal/ui/messages/render.go", "source_location": "L1039"}, {"caller_nid": "messages_render_renderitalics", "callee": "Render", "is_member_call": true, "source_file": "/Users/siltala/dev/personal/slk/internal/ui/messages/render.go", "source_location": "L1039"}, {"caller_nid": "messages_render_isitalicwordrune", "callee": "IsLetter", "is_member_call": false, "source_file": "/Users/siltala/dev/personal/slk/internal/ui/messages/render.go", "source_location": "L1053"}, {"caller_nid": "messages_render_isitalicwordrune", "callee": "IsDigit", "is_member_call": false, "source_file": "/Users/siltala/dev/personal/slk/internal/ui/messages/render.go", "source_location": "L1053"}, {"caller_nid": "messages_render_plainlines", "callee": "Strip", "is_member_call": false, "source_file": "/Users/siltala/dev/personal/slk/internal/ui/messages/render.go", "source_location": "L1091"}, {"caller_nid": "messages_render_plainlines", "callee": "Split", "is_member_call": false, "source_file": "/Users/siltala/dev/personal/slk/internal/ui/messages/render.go", "source_location": "L1092"}, {"caller_nid": "messages_render_plainlines", "callee": "make", "is_member_call": false, "source_file": "/Users/siltala/dev/personal/slk/internal/ui/messages/render.go", "source_location": "L1093"}, {"caller_nid": "messages_render_buildplainline", "callee": "NewGraphemes", "is_member_call": false, "source_file": "/Users/siltala/dev/personal/slk/internal/ui/messages/render.go", "source_location": "L1107"}, {"caller_nid": "messages_render_buildplainline", "callee": "make", "is_member_call": false, "source_file": "/Users/siltala/dev/personal/slk/internal/ui/messages/render.go", "source_location": "L1108"}, {"caller_nid": "messages_render_buildplainline", "callee": "Next", "is_member_call": true, "source_file": "/Users/siltala/dev/personal/slk/internal/ui/messages/render.go", "source_location": "L1110"}, {"caller_nid": "messages_render_buildplainline", "callee": "Str", "is_member_call": true, "source_file": "/Users/siltala/dev/personal/slk/internal/ui/messages/render.go", "source_location": "L1111"}, {"caller_nid": "messages_render_buildplainline", "callee": "Width", "is_member_call": true, "source_file": "/Users/siltala/dev/personal/slk/internal/ui/messages/render.go", "source_location": "L1112"}, {"caller_nid": "messages_render_buildplainline", "callee": "append", "is_member_call": false, "source_file": "/Users/siltala/dev/personal/slk/internal/ui/messages/render.go", "source_location": "L1126"}, {"caller_nid": "messages_render_buildplainline", "callee": "append", "is_member_call": false, "source_file": "/Users/siltala/dev/personal/slk/internal/ui/messages/render.go", "source_location": "L1131"}, {"caller_nid": "messages_render_plainlines", "callee": "plainLines", "is_member_call": false, "source_file": "/Users/siltala/dev/personal/slk/internal/ui/messages/render.go", "source_location": "L1168"}, {"caller_nid": "messages_render_displaywidthofplain", "callee": "displayWidthOfPlain", "is_member_call": false, "source_file": "/Users/siltala/dev/personal/slk/internal/ui/messages/render.go", "source_location": "L1171"}, {"caller_nid": "messages_render_slicecolumns", "callee": "sliceColumns", "is_member_call": false, "source_file": "/Users/siltala/dev/personal/slk/internal/ui/messages/render.go", "source_location": "L1174"}]}